[{"score":0,"score_max":0,"score_min":0,"flag":1,"level":0,"start_time":1594170000000,"end_time":1594170059999},{"score":0,"score_max":0,"score_min":0,"flag":1,"level":0,"start_time":1594170060000,"end_time":1594170119999},{"score":0,"score_max":0,"score_min":0,"flag":1,"level":0,"start_time":1594170120000,"end_time":1594170179999},{"score":0,"score_max":0,"score_min":0,"flag":1,"level":0,"start_time":1594170180000,"end_time":1594170239999},{"score":0,"score_max":0,"score_min":0,"flag":1,"level":0,"start_time":1594170240000,"end_time":1594170299999},{"score":0,"score_max":0,"score_min":0,"flag":1,"level":0,"start_time":1594170300000,"end_time":1594170359999},{"score":0,"score_max":0,"score_min":0,"flag":1,"level":0,"start_time":1594170360000,"end_time":1594170419999},{"score":0,"score_max":0,"score_min":0,"flag":1,"level":0,"start_time":1594170420000,"end_time":1594170479999},{"score":0,"score_max":0,"score_min":0,"flag":1,"level":0,"start_time":1594170480000,"end_time":1594170539999},{"score":0,"score_max":0,"score_min":0,"flag":1,"level":0,"start_time":1594170540000,"end_time":1594170599999},{"score":0,"score_max":0,"score_min":0,"flag":1,"level":0,"start_time":1594170600000,"end_time":1594170659999},{"score":0,"score_max":0,"score_min":0,"flag":1,"level":0,"start_time":1594170660000,"end_time":1594170719999},{"score":2,"score_max":6,"score_min":0,"flag":1,"level":0,"start_time":1594170720000,"end_time":1594170779999},{"score":0,"score_max":0,"score_min":0,"flag":1,"level":0,"start_time":1594170780000,"end_time":1594170839999},{"score":0,"score_max":0,"score_min":0,"flag":1,"level":0,"start_time":1594170840000,"end_time":1594170899999},{"score":0,"score_max":0,"score_min":0,"flag":1,"level":0,"start_time":1594170900000,"end_time":1594170959999},{"score":0,"score_max":0,"score_min":0,"flag":1,"level":0,"start_time":1594170960000,"end_time":1594171019999},{"score":0,"score_max":0,"score_min":0,"flag":1,"level":0,"start_time":1594171020000,"end_time":1594171079999},{"score":0,"score_max":0,"score_min":0,"flag":1,"level":0,"start_time":1594171080000,"end_time":1594171139999},{"score":0,"score_max":0,"score_min":0,"flag":1,"level":0,"start_time":1594171140000,"end_time":1594171199999},{"score":0,"score_max":0,"score_min":0,"flag":1,"level":0,"start_time":1594171200000,"end_time":1594171259999},{"score":0,"score_max":0,"score_min":0,"flag":1,"level":0,"start_time":1594171260000,"end_time":1594171319999},{"score":0,"score_max":0,"score_min":0,"flag":1,"level":0,"start_time":1594171320000,"end_time":1594171379999},{"score":0,"score_max":0,"score_min":0,"flag":1,"level":0,"start_time":1594171380000,"end_time":1594171439999},{"score":0,"score_max":0,"score_min":0,"flag":1,"level":0,"start_time":1594171440000,"end_time":1594171499999},{"score":0,"score_max":0,"score_min":0,"flag":1,"level":0,"start_time":1594171500000,"end_time":1594171559999},{"score":0,"score_max":0,"score_min":0,"flag":1,"level":0,"start_time":1594171560000,"end_time":1594171619999},{"score":0,"score_max":0,"score_min":0,"flag":1,"level":0,"start_time":1594171620000,"end_time":1594171679999},{"score":0,"score_max":0,"score_min":0,"flag":1,"level":0,"start_time":1594171680000,"end_time":1594171739999},{"score":0,"score_max":0,"score_min":0,"flag":1,"level":0,"start_time":1594171740000,"end_time":1594171799999},{"score":0,"score_max":0,"score_min":0,"flag":1,"level":0,"start_time":1594171800000,"end_time":1594171859999},{"score":0,"score_max":0,"score_min":0,"flag":1,"level":0,"start_time":1594171860000,"end_time":1594171919999},{"score":0,"score_max":0,"score_min":0,"flag":1,"level":0,"start_time":1594171920000,"end_time":1594171979999},{"score":0,"score_max":0,"score_min":0,"flag":1,"level":0,"start_time":1594171980000,"end_time":1594172039999},{"score":0,"score_max":0,"score_min":0,"flag":1,"level":0,"start_time":1594172040000,"end_time":1594172099999},{"score":0,"score_max":0,"score_min":0,"flag":1,"level":0,"start_time":1594172100000,"end_time":1594172159999},{"score":0,"score_max":0,"score_min":0,"flag":1,"level":0,"start_time":1594172160000,"end_time":1594172219999},{"score":0,"score_max":0,"score_min":0,"flag":1,"level":0,"start_time":1594172220000,"end_time":1594172279999},{"score":0,"score_max":0,"score_min":0,"flag":1,"level":0,"start_time":1594172280000,"end_time":1594172339999},{"score":0,"score_max":0,"score_min":0,"flag":1,"level":0,"start_time":1594172340000,"end_time":1594172399999},{"score":0,"score_max":0,"score_min":0,"flag":1,"level":0,"start_time":1594172400000,"end_time":1594172459999},{"score":0,"score_max":0,"score_min":0,"flag":1,"level":0,"start_time":1594172460000,"end_time":1594172519999},{"score":1,"score_max":6,"score_min":0,"flag":1,"level":0,"start_time":1594172520000,"end_time":1594172579999},{"score":8,"score_max":10,"score_min":6,"flag":1,"level":0,"start_time":1594172580000,"end_time":1594172639999},{"score":1,"score_max":9,"score_min":0,"flag":1,"level":0,"start_time":1594172640000,"end_time":1594172699999},{"score":0,"score_max":0,"score_min":0,"flag":1,"level":0,"start_time":1594172700000,"end_time":1594172759999},{"score":0,"score_max":2,"score_min":0,"flag":1,"level":0,"start_time":1594172760000,"end_time":1594172819999},{"score":3,"score_max":5,"score_min":2,"flag":1,"level":0,"start_time":1594172820000,"end_time":1594172879999},{"score":4,"score_max":17,"score_min":2,"flag":1,"level":0,"start_time":1594172880000,"end_time":1594172939999},{"score":39,"score_max":62,"score_min":10,"flag":1,"level":0,"start_time":1594172940000,"end_time":1594172999999},{"score":0,"score_max":9,"score_min":0,"flag":1,"level":0,"start_time":1594173000000,"end_time":1594173059999},{"score":0,"score_max":0,"score_min":0,"flag":1,"level":0,"start_time":1594173060000,"end_time":1594173119999},{"score":0,"score_max":0,"score_min":0,"flag":1,"level":0,"start_time":1594173120000,"end_time":1594173179999},{"score":0,"score_max":0,"score_min":0,"flag":1,"level":0,"start_time":1594173180000,"end_time":1594173239999},{"score":0,"score_max":0,"score_min":0,"flag":1,"level":0,"start_time":1594173240000,"end_time":1594173299999},{"score":0,"score_max":0,"score_min":0,"flag":1,"level":0,"start_time":1594173300000,"end_time":1594173359999},{"score":0,"score_max":0,"score_min":0,"flag":1,"level":0,"start_time":1594173360000,"end_time":1594173419999},{"score":0,"score_max":0,"score_min":0,"flag":1,"level":0,"start_time":1594173420000,"end_time":1594173479999},{"score":0,"score_max":0,"score_min":0,"flag":1,"level":0,"start_time":1594173480000,"end_time":1594173539999},{"score":0,"score_max":0,"score_min":0,"flag":1,"level":0,"start_time":1594173540000,"end_time":1594173599999}]