[{"calorie":0.0,"count":0,"distance":0.0,"speed":0.0},{"calorie":0.0,"count":0,"distance":0.0,"speed":0.0},{"calorie":0.0,"count":0,"distance":0.0,"speed":0.0},{"calorie":0.0,"count":0,"distance":0.0,"speed":0.0},{"calorie":0.0,"count":0,"distance":0.0,"speed":0.0},{"calorie":0.0,"count":0,"distance":0.0,"speed":0.0},{"calorie":0.0,"count":0,"distance":0.0,"speed":0.0},{"calorie":0.6044922,"count":10,"distance":10.402344,"speed":7.460104942321777},{"calorie":0.0,"count":0,"distance":0.0,"speed":0.0},{"calorie":0.0,"count":0,"distance":0.0,"speed":0.0},{"calorie":0.0,"count":0,"distance":0.0,"speed":0.0},{"calorie":0.0,"count":0,"distance":0.0,"speed":0.0},{"calorie":0.0,"count":0,"distance":0.0,"speed":0.0},{"calorie":0.0,"count":0,"distance":0.0,"speed":0.0},{"calorie":0.0,"count":0,"distance":0.0,"speed":0.0},{"calorie":0.0,"count":0,"distance":0.0,"speed":0.0},{"calorie":0.0,"count":0,"distance":0.0,"speed":0.0},{"calorie":0.0,"count":0,"distance":0.0,"speed":0.0},{"calorie":0.0,"count":0,"distance":0.0,"speed":0.0},{"calorie":0.0,"count":0,"distance":0.0,"speed":0.0},{"calorie":0.0,"count":0,"distance":0.0,"speed":0.0},{"calorie":0.0,"count":0,"distance":0.0,"speed":0.0},{"calorie":0.0,"count":0,"distance":0.0,"speed":0.0},{"calorie":0.0,"count":0,"distance":0.0,"speed":0.0},{"calorie":0.0,"count":0,"distance":0.0,"speed":0.0},{"calorie":0.0,"count":0,"distance":0.0,"speed":0.0},{"calorie":0.0,"count":0,"distance":0.0,"speed":0.0},{"calorie":0.0,"count":0,"distance":0.0,"speed":0.0},{"calorie":0.0,"count":0,"distance":0.0,"speed":0.0},{"calorie":0.0,"count":0,"distance":0.0,"speed":0.0},{"calorie":0.0,"count":0,"distance":0.0,"speed":0.0},{"calorie":0.0,"count":0,"distance":0.0,"speed":0.0},{"calorie":0.0,"count":0,"distance":0.0,"speed":0.0},{"calorie":0.0,"count":0,"distance":0.0,"speed":0.0},{"calorie":0.0,"count":0,"distance":0.0,"speed":0.0},{"calorie":0.0,"count":0,"distance":0.0,"speed":0.0},{"calorie":0.0,"count":0,"distance":0.0,"speed":0.0},{"calorie":0.0,"count":0,"distance":0.0,"speed":0.0},{"calorie":0.0,"count":0,"distance":0.0,"speed":0.0},{"calorie":0.0,"count":0,"distance":0.0,"speed":0.0},{"calorie":0.0,"count":0,"distance":0.0,"speed":0.0},{"calorie":0.0,"count":0,"distance":0.0,"speed":0.0},{"calorie":0.0,"count":0,"distance":0.0,"speed":0.0},{"calorie":0.0,"count":0,"distance":0.0,"speed":0.0},{"calorie":1.3763428,"count":39,"distance":28.964844,"speed":5.110029697418213},{"calorie":0.0,"count":0,"distance":0.0,"speed":0.0},{"calorie":0.0,"count":0,"distance":0.0,"speed":0.0},{"calorie":26.142822199999998,"count":489,"distance":494.8007829999999,"speed":7.076379299163818},{"calorie":1.7805176,"count":50,"distance":38.445312,"speed":5.175111770629883},{"calorie":23.25044381306,"count":655,"distance":540.123658905957,"speed":6.6826372146606445},{"calorie":14.244300884472656,"count":227,"distance":240.1937255859375,"speed":8.86986255645752},{"calorie":4.459262604169312,"count":139,"distance":108.5942151430664,"speed":5.853919506072998},{"calorie":47.27846213828278,"count":1016,"distance":679.6287400327147,"speed":5.869399547576904},{"calorie":15.531738299999997,"count":439,"distance":343.101563,"speed":5.732512950897217},{"calorie":6.2105713399999996,"count":178,"distance":137.726563,"speed":5.603455543518066},{"calorie":1.9487305,"count":56,"distance":44.2343755,"speed":6.2965569496154785},{"calorie":7.61074587691269,"count":202,"distance":168.816087019104,"speed":6.0795416831970215},{"calorie":1.3199999630451202,"count":38,"distance":31.18000030517578,"speed":6.85451078414917},{"calorie":0.0,"count":0,"distance":0.0,"speed":0.0},{"calorie":0.0,"count":0,"distance":0.0,"speed":0.0},{"calorie":1.8599992841482162,"count":58,"distance":45.790000915527344,"speed":5.977297782897949},{"calorie":0.0,"count":0,"distance":0.0,"speed":0.0},{"calorie":5.142079106986618,"count":135,"distance":112.95141433511353,"speed":5.983249187469482},{"calorie":5.659999519586563,"count":154,"distance":130.2700071334839,"speed":5.848661422729492},{"calorie":3.683515653113022,"count":106,"distance":82.45359248092652,"speed":5.5204644203186035},{"calorie":0.0,"count":0,"distance":0.0,"speed":0.0},{"calorie":0.0,"count":0,"distance":0.0,"speed":0.0},{"calorie":0.0,"count":0,"distance":0.0,"speed":0.0},{"calorie":0.0,"count":0,"distance":0.0,"speed":0.0},{"calorie":0.6399999856948853,"count":19,"distance":14.680000305175781,"speed":5.299999713897705},{"calorie":0.49000000953674316,"count":15,"distance":12.130001068115234,"speed":6.379715442657471},{"calorie":0.0,"count":0,"distance":0.0,"speed":0.0},{"calorie":17.878818333378604,"count":532,"distance":400.55296141418455,"speed":5.283801078796387},{"calorie":3.998486311920929,"count":115,"distance":88.48999977111816,"speed":5.274038791656494},{"calorie":22.349287162124632,"count":603,"distance":474.4426535913086,"speed":5.202281475067139},{"calorie":10.82055659569187,"count":276,"distance":211.0835955722046,"speed":5.740697860717773},{"calorie":0.0,"count":0,"distance":0.0,"speed":0.0},{"calorie":0.0,"count":0,"distance":0.0,"speed":0.0},{"calorie":0.0,"count":0,"distance":0.0,"speed":0.0},{"calorie":1.7899999618530273,"count":52,"distance":39.63000011444092,"speed":4.915256500244141},{"calorie":3.7999991178512573,"count":118,"distance":94.68001174926758,"speed":5.875826835632324},{"calorie":0.0,"count":0,"distance":0.0,"speed":0.0},{"calorie":0.5899999737739563,"count":8,"distance":8.670000076293945,"speed":5.800000190734863},{"calorie":0.0,"count":0,"distance":0.0,"speed":0.0},{"calorie":5.140526708586121,"count":160,"distance":124.34437992504883,"speed":5.497074604034424},{"calorie":0.0,"count":0,"distance":0.0,"speed":0.0},{"calorie":0.0,"count":0,"distance":0.0,"speed":0.0},{"calorie":0.0,"count":0,"distance":0.0,"speed":0.0},{"calorie":0.7763672,"count":22,"distance":16.234375,"speed":4.945133209228516},{"calorie":0.0,"count":0,"distance":0.0,"speed":0.0},{"calorie":0.0,"count":0,"distance":0.0,"speed":0.0},{"calorie":0.0,"count":0,"distance":0.0,"speed":0.0},{"calorie":0.0,"count":0,"distance":0.0,"speed":0.0},{"calorie":0.0,"count":0,"distance":0.0,"speed":0.0},{"calorie":0.0,"count":0,"distance":0.0,"speed":0.0},{"calorie":0.0,"count":0,"distance":0.0,"speed":0.0},{"calorie":0.0,"count":0,"distance":0.0,"speed":0.0},{"calorie":0.0,"count":0,"distance":0.0,"speed":0.0},{"calorie":0.0,"count":0,"distance":0.0,"speed":0.0},{"calorie":0.41999998688697815,"count":12,"distance":9.739999771118164,"speed":6.134241104125977},{"calorie":1.4909668,"count":19,"distance":24.734375,"speed":22.068359375},{"calorie":0.0,"count":0,"distance":0.0,"speed":0.0},{"calorie":0.0,"count":0,"distance":0.0,"speed":0.0},{"calorie":1.4555664,"count":40,"distance":32.83203,"speed":6.083983898162842},{"calorie":0.8227539,"count":23,"distance":18.496094,"speed":5.17812967300415},{"calorie":2.1799995601177216,"count":69,"distance":55.03000473976135,"speed":6.748686790466309},{"calorie":1.1200000047683716,"count":19,"distance":20.229999542236328,"speed":6.600000858306885},{"calorie":1.1210938,"count":15,"distance":15.503906,"speed":9.697690963745117},{"calorie":9.36350560211258,"count":270,"distance":212.0656243297119,"speed":5.876048564910889},{"calorie":2.7971972270846557,"count":85,"distance":67.37750053405762,"speed":6.1839280128479},{"calorie":0.0,"count":0,"distance":0.0,"speed":0.0},{"calorie":1.546875,"count":26,"distance":23.9375,"speed":6.893051624298096},{"calorie":0.0,"count":0,"distance":0.0,"speed":0.0},{"calorie":0.0,"count":0,"distance":0.0,"speed":0.0},{"calorie":1.0651366821186066,"count":30,"distance":22.973437809265135,"speed":4.679769515991211},{"calorie":18.903984521661375,"count":533,"distance":421.69344216894535,"speed":5.819628715515137},{"calorie":38.30362094523926,"count":1185,"distance":851.9170290844727,"speed":5.662765026092529},{"calorie":6.899999976158142,"count":219,"distance":173.00999450683594,"speed":5.544364929199219},{"calorie":0.0,"count":0,"distance":0.0,"speed":0.0},{"calorie":0.0,"count":0,"distance":0.0,"speed":0.0},{"calorie":1.149999976158142,"count":34,"distance":26.299999237060547,"speed":5.299999713897705},{"calorie":6.464462041229859,"count":181,"distance":139.20094169316405,"speed":5.398683071136475},{"calorie":0.59155273,"count":17,"distance":13.375,"speed":6.4526801109313965},{"calorie":0.0,"count":0,"distance":0.0,"speed":0.0},{"calorie":0.0,"count":0,"distance":0.0,"speed":0.0},{"calorie":0.0,"count":0,"distance":0.0,"speed":0.0},{"calorie":0.43408203,"count":12,"distance":8.3515625,"speed":4.452229976654053},{"calorie":10.736826209536744,"count":302,"distance":232.1818733215332,"speed":5.110098838806152},{"calorie":26.98351789458313,"count":813,"distance":624.4486427954101,"speed":5.437770843505859},{"calorie":33.0231933,"count":653,"distance":603.5234460000001,"speed":8.050760269165039},{"calorie":25.7250974,"count":417,"distance":439.07421999999997,"speed":9.844613075256348},{"calorie":27.832031299999997,"count":614,"distance":537.492184,"speed":7.016879558563232},{"calorie":10.87011704,"count":281,"distance":223.3554658,"speed":5.412435531616211},{"calorie":1.1479492,"count":27,"distance":23.0742185,"speed":7.124295711517334},{"calorie":0.0,"count":0,"distance":0.0,"speed":0.0},{"calorie":18.56795803215637,"count":508,"distance":391.3420165627441,"speed":5.420785903930664},{"calorie":26.17862317377396,"count":589,"distance":503.3721801144409,"speed":6.655569553375244},{"calorie":6.93530277,"count":178,"distance":141.48438,"speed":5.26519250869751},{"calorie":19.960937499999996,"count":570,"distance":444.921874,"speed":5.4741010665893555},{"calorie":14.165771449999998,"count":375,"distance":304.7890645,"speed":6.19571590423584},{"calorie":20.608710659129336,"count":574,"distance":442.49092705725104,"speed":5.7217888832092285},{"calorie":9.811307466319656,"count":300,"distance":224.36688804626465,"speed":5.6866865158081055},{"calorie":0.9299996495246887,"count":29,"distance":21.930002212524414,"speed":5.652838706970215},{"calorie":12.925124115270997,"count":339,"distance":255.74855047973634,"speed":5.284579277038574}]