[{"mCalorie":0.4399999976158142,"mDistance":10.830000877380371,"mNowHealthyStep":0,"mRunStepCount":0,"mSpeed":8.316295623779297,"mStartTime":0,"mStepCount":13,"mTimeUnit":600000,"mTotalActiveTime":4688.1454102098705,"mWalkStepCount":13},{"mCalorie":0.0,"mDistance":0.0,"mNowHealthyStep":0,"mRunStepCount":0,"mSpeed":0.0,"mStartTime":0,"mStepCount":0,"mTimeUnit":600000,"mTotalActiveTime":0.0,"mWalkStepCount":0},{"mCalorie":0.0,"mDistance":0.0,"mNowHealthyStep":0,"mRunStepCount":0,"mSpeed":0.0,"mStartTime":0,"mStepCount":0,"mTimeUnit":600000,"mTotalActiveTime":0.0,"mWalkStepCount":0},{"mCalorie":0.0,"mDistance":0.0,"mNowHealthyStep":0,"mRunStepCount":0,"mSpeed":0.0,"mStartTime":0,"mStepCount":0,"mTimeUnit":600000,"mTotalActiveTime":0.0,"mWalkStepCount":0},{"mCalorie":0.0,"mDistance":0.0,"mNowHealthyStep":0,"mRunStepCount":0,"mSpeed":0.0,"mStartTime":0,"mStepCount":0,"mTimeUnit":600000,"mTotalActiveTime":0.0,"mWalkStepCount":0},{"mCalorie":0.0,"mDistance":0.0,"mNowHealthyStep":0,"mRunStepCount":0,"mSpeed":0.0,"mStartTime":0,"mStepCount":0,"mTimeUnit":600000,"mTotalActiveTime":0.0,"mWalkStepCount":0},{"mCalorie":0.0,"mDistance":0.0,"mNowHealthyStep":0,"mRunStepCount":0,"mSpeed":0.0,"mStartTime":0,"mStepCount":0,"mTimeUnit":600000,"mTotalActiveTime":0.0,"mWalkStepCount":0},{"mCalorie":0.0,"mDistance":0.0,"mNowHealthyStep":0,"mRunStepCount":0,"mSpeed":0.0,"mStartTime":0,"mStepCount":0,"mTimeUnit":600000,"mTotalActiveTime":0.0,"mWalkStepCount":0},{"mCalorie":0.0,"mDistance":0.0,"mNowHealthyStep":0,"mRunStepCount":0,"mSpeed":0.0,"mStartTime":0,"mStepCount":0,"mTimeUnit":600000,"mTotalActiveTime":0.0,"mWalkStepCount":0},{"mCalorie":0.0,"mDistance":0.0,"mNowHealthyStep":0,"mRunStepCount":0,"mSpeed":0.0,"mStartTime":0,"mStepCount":0,"mTimeUnit":600000,"mTotalActiveTime":0.0,"mWalkStepCount":0},{"mCalorie":0.0,"mDistance":0.0,"mNowHealthyStep":0,"mRunStepCount":0,"mSpeed":0.0,"mStartTime":0,"mStepCount":0,"mTimeUnit":600000,"mTotalActiveTime":0.0,"mWalkStepCount":0},{"mCalorie":0.0,"mDistance":0.0,"mNowHealthyStep":0,"mRunStepCount":0,"mSpeed":0.0,"mStartTime":0,"mStepCount":0,"mTimeUnit":600000,"mTotalActiveTime":0.0,"mWalkStepCount":0},{"mCalorie":0.0,"mDistance":0.0,"mNowHealthyStep":0,"mRunStepCount":0,"mSpeed":0.0,"mStartTime":0,"mStepCount":0,"mTimeUnit":600000,"mTotalActiveTime":0.0,"mWalkStepCount":0},{"mCalorie":0.0,"mDistance":0.0,"mNowHealthyStep":0,"mRunStepCount":0,"mSpeed":0.0,"mStartTime":0,"mStepCount":0,"mTimeUnit":600000,"mTotalActiveTime":0.0,"mWalkStepCount":0},{"mCalorie":0.0,"mDistance":0.0,"mNowHealthyStep":0,"mRunStepCount":0,"mSpeed":0.0,"mStartTime":0,"mStepCount":0,"mTimeUnit":600000,"mTotalActiveTime":0.0,"mWalkStepCount":0},{"mCalorie":0.0,"mDistance":0.0,"mNowHealthyStep":0,"mRunStepCount":0,"mSpeed":0.0,"mStartTime":0,"mStepCount":0,"mTimeUnit":600000,"mTotalActiveTime":0.0,"mWalkStepCount":0},{"mCalorie":0.0,"mDistance":0.0,"mNowHealthyStep":0,"mRunStepCount":0,"mSpeed":0.0,"mStartTime":0,"mStepCount":0,"mTimeUnit":600000,"mTotalActiveTime":0.0,"mWalkStepCount":0},{"mCalorie":0.0,"mDistance":0.0,"mNowHealthyStep":0,"mRunStepCount":0,"mSpeed":0.0,"mStartTime":0,"mStepCount":0,"mTimeUnit":600000,"mTotalActiveTime":0.0,"mWalkStepCount":0},{"mCalorie":0.0,"mDistance":0.0,"mNowHealthyStep":0,"mRunStepCount":0,"mSpeed":0.0,"mStartTime":0,"mStepCount":0,"mTimeUnit":600000,"mTotalActiveTime":0.0,"mWalkStepCount":0},{"mCalorie":0.0,"mDistance":0.0,"mNowHealthyStep":0,"mRunStepCount":0,"mSpeed":0.0,"mStartTime":0,"mStepCount":0,"mTimeUnit":600000,"mTotalActiveTime":0.0,"mWalkStepCount":0},{"mCalorie":0.0,"mDistance":0.0,"mNowHealthyStep":0,"mRunStepCount":0,"mSpeed":0.0,"mStartTime":0,"mStepCount":0,"mTimeUnit":600000,"mTotalActiveTime":0.0,"mWalkStepCount":0},{"mCalorie":0.0,"mDistance":0.0,"mNowHealthyStep":0,"mRunStepCount":0,"mSpeed":0.0,"mStartTime":0,"mStepCount":0,"mTimeUnit":600000,"mTotalActiveTime":0.0,"mWalkStepCount":0},{"mCalorie":0.0,"mDistance":0.0,"mNowHealthyStep":0,"mRunStepCount":0,"mSpeed":0.0,"mStartTime":0,"mStepCount":0,"mTimeUnit":600000,"mTotalActiveTime":0.0,"mWalkStepCount":0},{"mCalorie":0.0,"mDistance":0.0,"mNowHealthyStep":0,"mRunStepCount":0,"mSpeed":0.0,"mStartTime":0,"mStepCount":0,"mTimeUnit":600000,"mTotalActiveTime":0.0,"mWalkStepCount":0},{"mCalorie":0.0,"mDistance":0.0,"mNowHealthyStep":0,"mRunStepCount":0,"mSpeed":0.0,"mStartTime":0,"mStepCount":0,"mTimeUnit":600000,"mTotalActiveTime":0.0,"mWalkStepCount":0},{"mCalorie":0.0,"mDistance":0.0,"mNowHealthyStep":0,"mRunStepCount":0,"mSpeed":0.0,"mStartTime":0,"mStepCount":0,"mTimeUnit":600000,"mTotalActiveTime":0.0,"mWalkStepCount":0},{"mCalorie":0.0,"mDistance":0.0,"mNowHealthyStep":0,"mRunStepCount":0,"mSpeed":0.0,"mStartTime":0,"mStepCount":0,"mTimeUnit":600000,"mTotalActiveTime":0.0,"mWalkStepCount":0},{"mCalorie":0.0,"mDistance":0.0,"mNowHealthyStep":0,"mRunStepCount":0,"mSpeed":0.0,"mStartTime":0,"mStepCount":0,"mTimeUnit":600000,"mTotalActiveTime":0.0,"mWalkStepCount":0},{"mCalorie":0.0,"mDistance":0.0,"mNowHealthyStep":0,"mRunStepCount":0,"mSpeed":0.0,"mStartTime":0,"mStepCount":0,"mTimeUnit":600000,"mTotalActiveTime":0.0,"mWalkStepCount":0},{"mCalorie":0.0,"mDistance":0.0,"mNowHealthyStep":0,"mRunStepCount":0,"mSpeed":0.0,"mStartTime":0,"mStepCount":0,"mTimeUnit":600000,"mTotalActiveTime":0.0,"mWalkStepCount":0},{"mCalorie":0.0,"mDistance":0.0,"mNowHealthyStep":0,"mRunStepCount":0,"mSpeed":0.0,"mStartTime":0,"mStepCount":0,"mTimeUnit":600000,"mTotalActiveTime":0.0,"mWalkStepCount":0},{"mCalorie":0.0,"mDistance":0.0,"mNowHealthyStep":0,"mRunStepCount":0,"mSpeed":0.0,"mStartTime":0,"mStepCount":0,"mTimeUnit":600000,"mTotalActiveTime":0.0,"mWalkStepCount":0},{"mCalorie":0.0,"mDistance":0.0,"mNowHealthyStep":0,"mRunStepCount":0,"mSpeed":0.0,"mStartTime":0,"mStepCount":0,"mTimeUnit":600000,"mTotalActiveTime":0.0,"mWalkStepCount":0},{"mCalorie":0.0,"mDistance":0.0,"mNowHealthyStep":0,"mRunStepCount":0,"mSpeed":0.0,"mStartTime":0,"mStepCount":0,"mTimeUnit":600000,"mTotalActiveTime":0.0,"mWalkStepCount":0},{"mCalorie":0.0,"mDistance":0.0,"mNowHealthyStep":0,"mRunStepCount":0,"mSpeed":0.0,"mStartTime":0,"mStepCount":0,"mTimeUnit":600000,"mTotalActiveTime":0.0,"mWalkStepCount":0},{"mCalorie":0.0,"mDistance":0.0,"mNowHealthyStep":0,"mRunStepCount":0,"mSpeed":0.0,"mStartTime":0,"mStepCount":0,"mTimeUnit":600000,"mTotalActiveTime":0.0,"mWalkStepCount":0},{"mCalorie":0.0,"mDistance":0.0,"mNowHealthyStep":0,"mRunStepCount":0,"mSpeed":0.0,"mStartTime":0,"mStepCount":0,"mTimeUnit":600000,"mTotalActiveTime":0.0,"mWalkStepCount":0},{"mCalorie":0.0,"mDistance":0.0,"mNowHealthyStep":0,"mRunStepCount":0,"mSpeed":0.0,"mStartTime":0,"mStepCount":0,"mTimeUnit":600000,"mTotalActiveTime":0.0,"mWalkStepCount":0},{"mCalorie":0.0,"mDistance":0.0,"mNowHealthyStep":0,"mRunStepCount":0,"mSpeed":0.0,"mStartTime":0,"mStepCount":0,"mTimeUnit":600000,"mTotalActiveTime":0.0,"mWalkStepCount":0},{"mCalorie":0.0,"mDistance":0.0,"mNowHealthyStep":0,"mRunStepCount":0,"mSpeed":0.0,"mStartTime":0,"mStepCount":0,"mTimeUnit":600000,"mTotalActiveTime":0.0,"mWalkStepCount":0},{"mCalorie":0.0,"mDistance":0.0,"mNowHealthyStep":0,"mRunStepCount":0,"mSpeed":0.0,"mStartTime":0,"mStepCount":0,"mTimeUnit":600000,"mTotalActiveTime":0.0,"mWalkStepCount":0},{"mCalorie":0.0,"mDistance":0.0,"mNowHealthyStep":0,"mRunStepCount":0,"mSpeed":0.0,"mStartTime":0,"mStepCount":0,"mTimeUnit":600000,"mTotalActiveTime":0.0,"mWalkStepCount":0},{"mCalorie":0.0,"mDistance":0.0,"mNowHealthyStep":0,"mRunStepCount":0,"mSpeed":0.0,"mStartTime":0,"mStepCount":0,"mTimeUnit":600000,"mTotalActiveTime":0.0,"mWalkStepCount":0},{"mCalorie":0.0,"mDistance":0.0,"mNowHealthyStep":0,"mRunStepCount":0,"mSpeed":0.0,"mStartTime":0,"mStepCount":0,"mTimeUnit":600000,"mTotalActiveTime":0.0,"mWalkStepCount":0},{"mCalorie":0.0,"mDistance":0.0,"mNowHealthyStep":0,"mRunStepCount":0,"mSpeed":0.0,"mStartTime":0,"mStepCount":0,"mTimeUnit":600000,"mTotalActiveTime":0.0,"mWalkStepCount":0},{"mCalorie":0.0,"mDistance":0.0,"mNowHealthyStep":0,"mRunStepCount":0,"mSpeed":0.0,"mStartTime":0,"mStepCount":0,"mTimeUnit":600000,"mTotalActiveTime":0.0,"mWalkStepCount":0},{"mCalorie":0.6600000262260437,"mDistance":16.31999969482422,"mNowHealthyStep":0,"mRunStepCount":0,"mSpeed":6.300000190734863,"mStartTime":0,"mStepCount":20,"mTimeUnit":600000,"mTotalActiveTime":9325.713828988642,"mWalkStepCount":20},{"mCalorie":0.0,"mDistance":0.0,"mNowHealthyStep":0,"mRunStepCount":0,"mSpeed":0.0,"mStartTime":0,"mStepCount":0,"mTimeUnit":600000,"mTotalActiveTime":0.0,"mWalkStepCount":0},{"mCalorie":4.739999830722809,"mDistance":109.17000102996826,"mNowHealthyStep":0,"mRunStepCount":0,"mSpeed":5.690335273742676,"mStartTime":0,"mStepCount":134,"mTimeUnit":600000,"mTotalActiveTime":69066.57884429957,"mWalkStepCount":134},{"mCalorie":29.519993901252747,"mDistance":682.5401306152344,"mNowHealthyStep":0,"mRunStepCount":28,"mSpeed":6.170135021209717,"mStartTime":0,"mStepCount":870,"mTimeUnit":600000,"mTotalActiveTime":398231.8705540991,"mWalkStepCount":842},{"mCalorie":0.9399999976158142,"mDistance":19.920000076293945,"mNowHealthyStep":0,"mRunStepCount":4,"mSpeed":7.700000286102295,"mStartTime":0,"mStepCount":22,"mTimeUnit":600000,"mTotalActiveTime":9313.246442872342,"mWalkStepCount":18},{"mCalorie":0.0,"mDistance":0.0,"mNowHealthyStep":0,"mRunStepCount":0,"mSpeed":0.0,"mStartTime":0,"mStepCount":0,"mTimeUnit":600000,"mTotalActiveTime":0.0,"mWalkStepCount":0},{"mCalorie":45.37999880313873,"mDistance":596.250057220459,"mNowHealthyStep":0,"mRunStepCount":0,"mSpeed":5.701187610626221,"mStartTime":0,"mStepCount":920,"mTimeUnit":600000,"mTotalActiveTime":376500.53154638316,"mWalkStepCount":920},{"mCalorie":1.8700000047683716,"mDistance":43.03999900817871,"mNowHealthyStep":0,"mRunStepCount":0,"mSpeed":5.856576919555664,"mStartTime":0,"mStepCount":53,"mTimeUnit":600000,"mTotalActiveTime":26456.41039024564,"mWalkStepCount":53},{"mCalorie":0.0,"mDistance":0.0,"mNowHealthyStep":0,"mRunStepCount":0,"mSpeed":0.0,"mStartTime":0,"mStepCount":0,"mTimeUnit":600000,"mTotalActiveTime":0.0,"mWalkStepCount":0},{"mCalorie":0.0,"mDistance":0.0,"mNowHealthyStep":0,"mRunStepCount":0,"mSpeed":0.0,"mStartTime":0,"mStepCount":0,"mTimeUnit":600000,"mTotalActiveTime":0.0,"mWalkStepCount":0},{"mCalorie":0.0,"mDistance":0.0,"mNowHealthyStep":0,"mRunStepCount":0,"mSpeed":0.0,"mStartTime":0,"mStepCount":0,"mTimeUnit":600000,"mTotalActiveTime":0.0,"mWalkStepCount":0},{"mCalorie":0.0,"mDistance":0.0,"mNowHealthyStep":0,"mRunStepCount":0,"mSpeed":0.0,"mStartTime":0,"mStepCount":0,"mTimeUnit":600000,"mTotalActiveTime":0.0,"mWalkStepCount":0},{"mCalorie":0.0,"mDistance":0.0,"mNowHealthyStep":0,"mRunStepCount":0,"mSpeed":0.0,"mStartTime":0,"mStepCount":0,"mTimeUnit":600000,"mTotalActiveTime":0.0,"mWalkStepCount":0},{"mCalorie":0.26999998092651367,"mDistance":6.229999542236328,"mNowHealthyStep":0,"mRunStepCount":0,"mSpeed":5.934939861297607,"mStartTime":0,"mStepCount":8,"mTimeUnit":600000,"mTotalActiveTime":3778.9765147084668,"mWalkStepCount":8},{"mCalorie":5.229999870061874,"mDistance":119.46999835968018,"mNowHealthyStep":0,"mRunStepCount":5,"mSpeed":6.36948299407959,"mStartTime":0,"mStepCount":146,"mTimeUnit":600000,"mTotalActiveTime":67523.84741723978,"mWalkStepCount":141},{"mCalorie":6.539999485015869,"mDistance":153.45999717712402,"mNowHealthyStep":0,"mRunStepCount":0,"mSpeed":5.731453895568848,"mStartTime":0,"mStepCount":196,"mTimeUnit":600000,"mTotalActiveTime":96390.19646487522,"mWalkStepCount":196},{"mCalorie":0.0,"mDistance":0.0,"mNowHealthyStep":0,"mRunStepCount":0,"mSpeed":0.0,"mStartTime":0,"mStepCount":0,"mTimeUnit":600000,"mTotalActiveTime":0.0,"mWalkStepCount":0},{"mCalorie":0.0,"mDistance":0.0,"mNowHealthyStep":0,"mRunStepCount":0,"mSpeed":0.0,"mStartTime":0,"mStepCount":0,"mTimeUnit":600000,"mTotalActiveTime":0.0,"mWalkStepCount":0},{"mCalorie":0.0,"mDistance":0.0,"mNowHealthyStep":0,"mRunStepCount":0,"mSpeed":0.0,"mStartTime":0,"mStepCount":0,"mTimeUnit":600000,"mTotalActiveTime":0.0,"mWalkStepCount":0},{"mCalorie":0.0,"mDistance":0.0,"mNowHealthyStep":0,"mRunStepCount":0,"mSpeed":0.0,"mStartTime":0,"mStepCount":0,"mTimeUnit":600000,"mTotalActiveTime":0.0,"mWalkStepCount":0},{"mCalorie":0.0,"mDistance":0.0,"mNowHealthyStep":0,"mRunStepCount":0,"mSpeed":0.0,"mStartTime":0,"mStepCount":0,"mTimeUnit":600000,"mTotalActiveTime":0.0,"mWalkStepCount":0},{"mCalorie":0.0,"mDistance":0.0,"mNowHealthyStep":0,"mRunStepCount":0,"mSpeed":0.0,"mStartTime":0,"mStepCount":0,"mTimeUnit":600000,"mTotalActiveTime":0.0,"mWalkStepCount":0},{"mCalorie":0.0,"mDistance":0.0,"mNowHealthyStep":0,"mRunStepCount":0,"mSpeed":0.0,"mStartTime":0,"mStepCount":0,"mTimeUnit":600000,"mTotalActiveTime":0.0,"mWalkStepCount":0},{"mCalorie":0.0,"mDistance":0.0,"mNowHealthyStep":0,"mRunStepCount":0,"mSpeed":0.0,"mStartTime":0,"mStepCount":0,"mTimeUnit":600000,"mTotalActiveTime":0.0,"mWalkStepCount":0},{"mCalorie":1.1299996376037598,"mDistance":28.370004653930664,"mNowHealthyStep":0,"mRunStepCount":0,"mSpeed":6.369165420532227,"mStartTime":0,"mStepCount":35,"mTimeUnit":600000,"mTotalActiveTime":16035.384545816352,"mWalkStepCount":35},{"mCalorie":3.4000000953674316,"mDistance":75.90000343322754,"mNowHealthyStep":0,"mRunStepCount":0,"mSpeed":5.41565465927124,"mStartTime":0,"mStepCount":97,"mTimeUnit":600000,"mTotalActiveTime":50453.73744582763,"mWalkStepCount":97},{"mCalorie":0.0,"mDistance":0.0,"mNowHealthyStep":0,"mRunStepCount":0,"mSpeed":0.0,"mStartTime":0,"mStepCount":0,"mTimeUnit":600000,"mTotalActiveTime":0.0,"mWalkStepCount":0},{"mCalorie":19.379996921867132,"mDistance":431.35993111133575,"mNowHealthyStep":0,"mRunStepCount":0,"mSpeed":5.363074779510498,"mStartTime":0,"mStepCount":573,"mTimeUnit":600000,"mTotalActiveTime":289553.2443941798,"mWalkStepCount":573},{"mCalorie":0.0,"mDistance":0.0,"mNowHealthyStep":0,"mRunStepCount":0,"mSpeed":0.0,"mStartTime":0,"mStepCount":0,"mTimeUnit":600000,"mTotalActiveTime":0.0,"mWalkStepCount":0},{"mCalorie":23.339998811483383,"mDistance":456.9499864578247,"mNowHealthyStep":0,"mRunStepCount":0,"mSpeed":5.2628607749938965,"mStartTime":0,"mStepCount":607,"mTimeUnit":600000,"mTotalActiveTime":312571.4330813321,"mWalkStepCount":607},{"mCalorie":10.749998971819878,"mDistance":249.7000026702881,"mNowHealthyStep":0,"mRunStepCount":0,"mSpeed":5.715933799743652,"mStartTime":0,"mStepCount":307,"mTimeUnit":600000,"mTotalActiveTime":157265.6436226062,"mWalkStepCount":307},{"mCalorie":0.2800000011920929,"mDistance":7.420000076293945,"mNowHealthyStep":0,"mRunStepCount":0,"mSpeed":12.300000190734863,"mStartTime":0,"mStepCount":9,"mTimeUnit":600000,"mTotalActiveTime":2171.7073057266593,"mWalkStepCount":9},{"mCalorie":0.0,"mDistance":0.0,"mNowHealthyStep":0,"mRunStepCount":0,"mSpeed":0.0,"mStartTime":0,"mStepCount":0,"mTimeUnit":600000,"mTotalActiveTime":0.0,"mWalkStepCount":0},{"mCalorie":0.0,"mDistance":0.0,"mNowHealthyStep":0,"mRunStepCount":0,"mSpeed":0.0,"mStartTime":0,"mStepCount":0,"mTimeUnit":600000,"mTotalActiveTime":0.0,"mWalkStepCount":0},{"mCalorie":0.0,"mDistance":0.0,"mNowHealthyStep":0,"mRunStepCount":0,"mSpeed":0.0,"mStartTime":0,"mStepCount":0,"mTimeUnit":600000,"mTotalActiveTime":0.0,"mWalkStepCount":0},{"mCalorie":0.0,"mDistance":0.0,"mNowHealthyStep":0,"mRunStepCount":0,"mSpeed":0.0,"mStartTime":0,"mStepCount":0,"mTimeUnit":600000,"mTotalActiveTime":0.0,"mWalkStepCount":0},{"mCalorie":0.0,"mDistance":0.0,"mNowHealthyStep":0,"mRunStepCount":0,"mSpeed":0.0,"mStartTime":0,"mStepCount":0,"mTimeUnit":600000,"mTotalActiveTime":0.0,"mWalkStepCount":0},{"mCalorie":0.0,"mDistance":0.0,"mNowHealthyStep":0,"mRunStepCount":0,"mSpeed":0.0,"mStartTime":0,"mStepCount":0,"mTimeUnit":600000,"mTotalActiveTime":0.0,"mWalkStepCount":0},{"mCalorie":3.5499988794326782,"mDistance":90.53002166748047,"mNowHealthyStep":0,"mRunStepCount":0,"mSpeed":5.950112342834473,"mStartTime":0,"mStepCount":114,"mTimeUnit":600000,"mTotalActiveTime":54773.43140841661,"mWalkStepCount":114},{"mCalorie":0.0,"mDistance":0.0,"mNowHealthyStep":0,"mRunStepCount":0,"mSpeed":0.0,"mStartTime":0,"mStepCount":0,"mTimeUnit":600000,"mTotalActiveTime":0.0,"mWalkStepCount":0},{"mCalorie":0.0,"mDistance":0.0,"mNowHealthyStep":0,"mRunStepCount":0,"mSpeed":0.0,"mStartTime":0,"mStepCount":0,"mTimeUnit":600000,"mTotalActiveTime":0.0,"mWalkStepCount":0},{"mCalorie":0.0,"mDistance":0.0,"mNowHealthyStep":0,"mRunStepCount":0,"mSpeed":0.0,"mStartTime":0,"mStepCount":0,"mTimeUnit":600000,"mTotalActiveTime":0.0,"mWalkStepCount":0},{"mCalorie":0.0,"mDistance":0.0,"mNowHealthyStep":0,"mRunStepCount":0,"mSpeed":0.0,"mStartTime":0,"mStepCount":0,"mTimeUnit":600000,"mTotalActiveTime":0.0,"mWalkStepCount":0},{"mCalorie":0.0,"mDistance":0.0,"mNowHealthyStep":0,"mRunStepCount":0,"mSpeed":0.0,"mStartTime":0,"mStepCount":0,"mTimeUnit":600000,"mTotalActiveTime":0.0,"mWalkStepCount":0},{"mCalorie":0.0,"mDistance":0.0,"mNowHealthyStep":0,"mRunStepCount":0,"mSpeed":0.0,"mStartTime":0,"mStepCount":0,"mTimeUnit":600000,"mTotalActiveTime":0.0,"mWalkStepCount":0},{"mCalorie":0.0,"mDistance":0.0,"mNowHealthyStep":0,"mRunStepCount":0,"mSpeed":0.0,"mStartTime":0,"mStepCount":0,"mTimeUnit":600000,"mTotalActiveTime":0.0,"mWalkStepCount":0},{"mCalorie":0.0,"mDistance":0.0,"mNowHealthyStep":0,"mRunStepCount":0,"mSpeed":0.0,"mStartTime":0,"mStepCount":0,"mTimeUnit":600000,"mTotalActiveTime":0.0,"mWalkStepCount":0},{"mCalorie":0.0,"mDistance":0.0,"mNowHealthyStep":0,"mRunStepCount":0,"mSpeed":0.0,"mStartTime":0,"mStepCount":0,"mTimeUnit":600000,"mTotalActiveTime":0.0,"mWalkStepCount":0},{"mCalorie":0.0,"mDistance":0.0,"mNowHealthyStep":0,"mRunStepCount":0,"mSpeed":0.0,"mStartTime":0,"mStepCount":0,"mTimeUnit":600000,"mTotalActiveTime":0.0,"mWalkStepCount":0},{"mCalorie":0.0,"mDistance":0.0,"mNowHealthyStep":0,"mRunStepCount":0,"mSpeed":0.0,"mStartTime":0,"mStepCount":0,"mTimeUnit":600000,"mTotalActiveTime":0.0,"mWalkStepCount":0},{"mCalorie":0.0,"mDistance":0.0,"mNowHealthyStep":0,"mRunStepCount":0,"mSpeed":0.0,"mStartTime":0,"mStepCount":0,"mTimeUnit":600000,"mTotalActiveTime":0.0,"mWalkStepCount":0},{"mCalorie":0.0,"mDistance":0.0,"mNowHealthyStep":0,"mRunStepCount":0,"mSpeed":0.0,"mStartTime":0,"mStepCount":0,"mTimeUnit":600000,"mTotalActiveTime":0.0,"mWalkStepCount":0},{"mCalorie":0.0,"mDistance":0.0,"mNowHealthyStep":0,"mRunStepCount":0,"mSpeed":0.0,"mStartTime":0,"mStepCount":0,"mTimeUnit":600000,"mTotalActiveTime":0.0,"mWalkStepCount":0},{"mCalorie":0.0,"mDistance":0.0,"mNowHealthyStep":0,"mRunStepCount":0,"mSpeed":0.0,"mStartTime":0,"mStepCount":0,"mTimeUnit":600000,"mTotalActiveTime":0.0,"mWalkStepCount":0},{"mCalorie":0.0,"mDistance":0.0,"mNowHealthyStep":0,"mRunStepCount":0,"mSpeed":0.0,"mStartTime":0,"mStepCount":0,"mTimeUnit":600000,"mTotalActiveTime":0.0,"mWalkStepCount":0},{"mCalorie":0.0,"mDistance":0.0,"mNowHealthyStep":0,"mRunStepCount":0,"mSpeed":0.0,"mStartTime":0,"mStepCount":0,"mTimeUnit":600000,"mTotalActiveTime":0.0,"mWalkStepCount":0},{"mCalorie":0.0,"mDistance":0.0,"mNowHealthyStep":0,"mRunStepCount":0,"mSpeed":0.0,"mStartTime":0,"mStepCount":0,"mTimeUnit":600000,"mTotalActiveTime":0.0,"mWalkStepCount":0},{"mCalorie":1.1399999260902405,"mDistance":22.939998626708984,"mNowHealthyStep":0,"mRunStepCount":0,"mSpeed":4.236029148101807,"mStartTime":0,"mStepCount":31,"mTimeUnit":600000,"mTotalActiveTime":19495.616191415047,"mWalkStepCount":31},{"mCalorie":0.0,"mDistance":0.0,"mNowHealthyStep":0,"mRunStepCount":0,"mSpeed":0.0,"mStartTime":0,"mStepCount":0,"mTimeUnit":600000,"mTotalActiveTime":0.0,"mWalkStepCount":0},{"mCalorie":0.0,"mDistance":0.0,"mNowHealthyStep":0,"mRunStepCount":0,"mSpeed":0.0,"mStartTime":0,"mStepCount":0,"mTimeUnit":600000,"mTotalActiveTime":0.0,"mWalkStepCount":0},{"mCalorie":0.0,"mDistance":0.0,"mNowHealthyStep":0,"mRunStepCount":0,"mSpeed":0.0,"mStartTime":0,"mStepCount":0,"mTimeUnit":600000,"mTotalActiveTime":0.0,"mWalkStepCount":0},{"mCalorie":3.3799994587898254,"mDistance":84.84001588821411,"mNowHealthyStep":0,"mRunStepCount":0,"mSpeed":6.210894584655762,"mStartTime":0,"mStepCount":106,"mTimeUnit":600000,"mTotalActiveTime":49175.53534717147,"mWalkStepCount":106},{"mCalorie":0.0,"mDistance":0.0,"mNowHealthyStep":0,"mRunStepCount":0,"mSpeed":0.0,"mStartTime":0,"mStepCount":0,"mTimeUnit":600000,"mTotalActiveTime":0.0,"mWalkStepCount":0},{"mCalorie":0.0,"mDistance":0.0,"mNowHealthyStep":0,"mRunStepCount":0,"mSpeed":0.0,"mStartTime":0,"mStepCount":0,"mTimeUnit":600000,"mTotalActiveTime":0.0,"mWalkStepCount":0},{"mCalorie":0.0,"mDistance":0.0,"mNowHealthyStep":0,"mRunStepCount":0,"mSpeed":0.0,"mStartTime":0,"mStepCount":0,"mTimeUnit":600000,"mTotalActiveTime":0.0,"mWalkStepCount":0},{"mCalorie":0.0,"mDistance":0.0,"mNowHealthyStep":0,"mRunStepCount":0,"mSpeed":0.0,"mStartTime":0,"mStepCount":0,"mTimeUnit":600000,"mTotalActiveTime":0.0,"mWalkStepCount":0},{"mCalorie":0.0,"mDistance":0.0,"mNowHealthyStep":0,"mRunStepCount":0,"mSpeed":0.0,"mStartTime":0,"mStepCount":0,"mTimeUnit":600000,"mTotalActiveTime":0.0,"mWalkStepCount":0},{"mCalorie":0.0,"mDistance":0.0,"mNowHealthyStep":0,"mRunStepCount":0,"mSpeed":0.0,"mStartTime":0,"mStepCount":0,"mTimeUnit":600000,"mTotalActiveTime":0.0,"mWalkStepCount":0},{"mCalorie":0.0,"mDistance":0.0,"mNowHealthyStep":0,"mRunStepCount":0,"mSpeed":0.0,"mStartTime":0,"mStepCount":0,"mTimeUnit":600000,"mTotalActiveTime":0.0,"mWalkStepCount":0},{"mCalorie":0.0,"mDistance":0.0,"mNowHealthyStep":0,"mRunStepCount":0,"mSpeed":0.0,"mStartTime":0,"mStepCount":0,"mTimeUnit":600000,"mTotalActiveTime":0.0,"mWalkStepCount":0},{"mCalorie":0.0,"mDistance":0.0,"mNowHealthyStep":0,"mRunStepCount":0,"mSpeed":0.0,"mStartTime":0,"mStepCount":0,"mTimeUnit":600000,"mTotalActiveTime":0.0,"mWalkStepCount":0},{"mCalorie":2.599999785423279,"mDistance":61.929996967315674,"mNowHealthyStep":0,"mRunStepCount":0,"mSpeed":6.038824081420898,"mStartTime":0,"mStepCount":79,"mTimeUnit":600000,"mTotalActiveTime":36919.1076643053,"mWalkStepCount":79},{"mCalorie":30.41999638080597,"mDistance":605.8699779510498,"mNowHealthyStep":0,"mRunStepCount":5,"mSpeed":5.588536739349365,"mStartTime":0,"mStepCount":951,"mTimeUnit":600000,"mTotalActiveTime":390286.7541854918,"mWalkStepCount":946},{"mCalorie":12.789999127388,"mDistance":276.0499939918518,"mNowHealthyStep":0,"mRunStepCount":47,"mSpeed":6.7456583976745605,"mStartTime":0,"mStepCount":329,"mTimeUnit":600000,"mTotalActiveTime":147321.416146696,"mWalkStepCount":282},{"mCalorie":0.0,"mDistance":0.0,"mNowHealthyStep":0,"mRunStepCount":0,"mSpeed":0.0,"mStartTime":0,"mStepCount":0,"mTimeUnit":600000,"mTotalActiveTime":0.0,"mWalkStepCount":0},{"mCalorie":11.609998643398285,"mDistance":296.76001167297363,"mNowHealthyStep":0,"mRunStepCount":0,"mSpeed":5.926131248474121,"mStartTime":0,"mStepCount":376,"mTimeUnit":600000,"mTotalActiveTime":180275.46418490852,"mWalkStepCount":376},{"mCalorie":0.6799999997019768,"mDistance":14.360000133514404,"mNowHealthyStep":0,"mRunStepCount":0,"mSpeed":5.015820503234863,"mStartTime":0,"mStepCount":19,"mTimeUnit":600000,"mTotalActiveTime":10306.589190131413,"mWalkStepCount":19},{"mCalorie":0.0,"mDistance":0.0,"mNowHealthyStep":0,"mRunStepCount":0,"mSpeed":0.0,"mStartTime":0,"mStepCount":0,"mTimeUnit":600000,"mTotalActiveTime":0.0,"mWalkStepCount":0},{"mCalorie":0.0,"mDistance":0.0,"mNowHealthyStep":0,"mRunStepCount":0,"mSpeed":0.0,"mStartTime":0,"mStepCount":0,"mTimeUnit":600000,"mTotalActiveTime":0.0,"mWalkStepCount":0},{"mCalorie":24.629997432231903,"mDistance":614.5999507904053,"mNowHealthyStep":0,"mRunStepCount":0,"mSpeed":5.71026086807251,"mStartTime":0,"mStepCount":785,"mTimeUnit":600000,"mTotalActiveTime":387470.89039111626,"mWalkStepCount":785},{"mCalorie":3.0999996662139893,"mDistance":68.44000053405762,"mNowHealthyStep":0,"mRunStepCount":0,"mSpeed":5.10632848739624,"mStartTime":0,"mStepCount":89,"mTimeUnit":600000,"mTotalActiveTime":48250.71678094617,"mWalkStepCount":89},{"mCalorie":0.7499997615814209,"mDistance":18.42999839782715,"mNowHealthyStep":0,"mRunStepCount":0,"mSpeed":6.834258556365967,"mStartTime":0,"mStepCount":23,"mTimeUnit":600000,"mTotalActiveTime":9708.148101943845,"mWalkStepCount":23},{"mCalorie":0.0,"mDistance":0.0,"mNowHealthyStep":0,"mRunStepCount":0,"mSpeed":0.0,"mStartTime":0,"mStepCount":0,"mTimeUnit":600000,"mTotalActiveTime":0.0,"mWalkStepCount":0},{"mCalorie":0.0,"mDistance":0.0,"mNowHealthyStep":0,"mRunStepCount":0,"mSpeed":0.0,"mStartTime":0,"mStepCount":0,"mTimeUnit":600000,"mTotalActiveTime":0.0,"mWalkStepCount":0},{"mCalorie":0.7999997735023499,"mDistance":19.080001831054688,"mNowHealthyStep":0,"mRunStepCount":0,"mSpeed":6.109249114990234,"mStartTime":0,"mStepCount":24,"mTimeUnit":600000,"mTotalActiveTime":11243.281342588805,"mWalkStepCount":24},{"mCalorie":0.0,"mDistance":0.0,"mNowHealthyStep":0,"mRunStepCount":0,"mSpeed":0.0,"mStartTime":0,"mStepCount":0,"mTimeUnit":600000,"mTotalActiveTime":0.0,"mWalkStepCount":0},{"mCalorie":0.0,"mDistance":0.0,"mNowHealthyStep":0,"mRunStepCount":0,"mSpeed":0.0,"mStartTime":0,"mStepCount":0,"mTimeUnit":600000,"mTotalActiveTime":0.0,"mWalkStepCount":0},{"mCalorie":0.0,"mDistance":0.0,"mNowHealthyStep":0,"mRunStepCount":0,"mSpeed":0.0,"mStartTime":0,"mStepCount":0,"mTimeUnit":600000,"mTotalActiveTime":0.0,"mWalkStepCount":0},{"mCalorie":0.0,"mDistance":0.0,"mNowHealthyStep":0,"mRunStepCount":0,"mSpeed":0.0,"mStartTime":0,"mStepCount":0,"mTimeUnit":600000,"mTotalActiveTime":0.0,"mWalkStepCount":0},{"mCalorie":0.0,"mDistance":0.0,"mNowHealthyStep":0,"mRunStepCount":0,"mSpeed":0.0,"mStartTime":0,"mStepCount":0,"mTimeUnit":600000,"mTotalActiveTime":0.0,"mWalkStepCount":0},{"mCalorie":0.0,"mDistance":0.0,"mNowHealthyStep":0,"mRunStepCount":0,"mSpeed":0.0,"mStartTime":0,"mStepCount":0,"mTimeUnit":600000,"mTotalActiveTime":0.0,"mWalkStepCount":0},{"mCalorie":0.0,"mDistance":0.0,"mNowHealthyStep":0,"mRunStepCount":0,"mSpeed":0.0,"mStartTime":0,"mStepCount":0,"mTimeUnit":600000,"mTotalActiveTime":0.0,"mWalkStepCount":0},{"mCalorie":0.0,"mDistance":0.0,"mNowHealthyStep":0,"mRunStepCount":0,"mSpeed":0.0,"mStartTime":0,"mStepCount":0,"mTimeUnit":600000,"mTotalActiveTime":0.0,"mWalkStepCount":0},{"mCalorie":0.0,"mDistance":0.0,"mNowHealthyStep":0,"mRunStepCount":0,"mSpeed":0.0,"mStartTime":0,"mStepCount":0,"mTimeUnit":600000,"mTotalActiveTime":0.0,"mWalkStepCount":0},{"mCalorie":0.0,"mDistance":0.0,"mNowHealthyStep":0,"mRunStepCount":0,"mSpeed":0.0,"mStartTime":0,"mStepCount":0,"mTimeUnit":600000,"mTotalActiveTime":0.0,"mWalkStepCount":0},{"mCalorie":0.0,"mDistance":0.0,"mNowHealthyStep":0,"mRunStepCount":0,"mSpeed":0.0,"mStartTime":0,"mStepCount":0,"mTimeUnit":600000,"mTotalActiveTime":0.0,"mWalkStepCount":0},{"mCalorie":0.0,"mDistance":0.0,"mNowHealthyStep":0,"mRunStepCount":0,"mSpeed":0.0,"mStartTime":0,"mStepCount":0,"mTimeUnit":600000,"mTotalActiveTime":0.0,"mWalkStepCount":0},{"mCalorie":0.0,"mDistance":0.0,"mNowHealthyStep":0,"mRunStepCount":0,"mSpeed":0.0,"mStartTime":0,"mStepCount":0,"mTimeUnit":600000,"mTotalActiveTime":0.0,"mWalkStepCount":0}]