[{"mCalorie":0.0,"mDistance":0.0,"mNowHealthyStep":0,"mRunStepCount":0,"mSpeed":0.0,"mStartTime":0,"mStepCount":0,"mTimeUnit":600000,"mTotalActiveTime":0.0,"mWalkStepCount":0},{"mCalorie":0.0,"mDistance":0.0,"mNowHealthyStep":0,"mRunStepCount":0,"mSpeed":0.0,"mStartTime":0,"mStepCount":0,"mTimeUnit":600000,"mTotalActiveTime":0.0,"mWalkStepCount":0},{"mCalorie":0.0,"mDistance":0.0,"mNowHealthyStep":0,"mRunStepCount":0,"mSpeed":0.0,"mStartTime":0,"mStepCount":0,"mTimeUnit":600000,"mTotalActiveTime":0.0,"mWalkStepCount":0},{"mCalorie":0.0,"mDistance":0.0,"mNowHealthyStep":0,"mRunStepCount":0,"mSpeed":0.0,"mStartTime":0,"mStepCount":0,"mTimeUnit":600000,"mTotalActiveTime":0.0,"mWalkStepCount":0},{"mCalorie":0.0,"mDistance":0.0,"mNowHealthyStep":0,"mRunStepCount":0,"mSpeed":0.0,"mStartTime":0,"mStepCount":0,"mTimeUnit":600000,"mTotalActiveTime":0.0,"mWalkStepCount":0},{"mCalorie":0.0,"mDistance":0.0,"mNowHealthyStep":0,"mRunStepCount":0,"mSpeed":0.0,"mStartTime":0,"mStepCount":0,"mTimeUnit":600000,"mTotalActiveTime":0.0,"mWalkStepCount":0},{"mCalorie":0.0,"mDistance":0.0,"mNowHealthyStep":0,"mRunStepCount":0,"mSpeed":0.0,"mStartTime":0,"mStepCount":0,"mTimeUnit":600000,"mTotalActiveTime":0.0,"mWalkStepCount":0},{"mCalorie":0.0,"mDistance":0.0,"mNowHealthyStep":0,"mRunStepCount":0,"mSpeed":0.0,"mStartTime":0,"mStepCount":0,"mTimeUnit":600000,"mTotalActiveTime":0.0,"mWalkStepCount":0},{"mCalorie":0.0,"mDistance":0.0,"mNowHealthyStep":0,"mRunStepCount":0,"mSpeed":0.0,"mStartTime":0,"mStepCount":0,"mTimeUnit":600000,"mTotalActiveTime":0.0,"mWalkStepCount":0},{"mCalorie":0.0,"mDistance":0.0,"mNowHealthyStep":0,"mRunStepCount":0,"mSpeed":0.0,"mStartTime":0,"mStepCount":0,"mTimeUnit":600000,"mTotalActiveTime":0.0,"mWalkStepCount":0},{"mCalorie":0.0,"mDistance":0.0,"mNowHealthyStep":0,"mRunStepCount":0,"mSpeed":0.0,"mStartTime":0,"mStepCount":0,"mTimeUnit":600000,"mTotalActiveTime":0.0,"mWalkStepCount":0},{"mCalorie":0.0,"mDistance":0.0,"mNowHealthyStep":0,"mRunStepCount":0,"mSpeed":0.0,"mStartTime":0,"mStepCount":0,"mTimeUnit":600000,"mTotalActiveTime":0.0,"mWalkStepCount":0},{"mCalorie":0.0,"mDistance":0.0,"mNowHealthyStep":0,"mRunStepCount":0,"mSpeed":0.0,"mStartTime":0,"mStepCount":0,"mTimeUnit":600000,"mTotalActiveTime":0.0,"mWalkStepCount":0},{"mCalorie":0.0,"mDistance":0.0,"mNowHealthyStep":0,"mRunStepCount":0,"mSpeed":0.0,"mStartTime":0,"mStepCount":0,"mTimeUnit":600000,"mTotalActiveTime":0.0,"mWalkStepCount":0},{"mCalorie":0.0,"mDistance":0.0,"mNowHealthyStep":0,"mRunStepCount":0,"mSpeed":0.0,"mStartTime":0,"mStepCount":0,"mTimeUnit":600000,"mTotalActiveTime":0.0,"mWalkStepCount":0},{"mCalorie":0.0,"mDistance":0.0,"mNowHealthyStep":0,"mRunStepCount":0,"mSpeed":0.0,"mStartTime":0,"mStepCount":0,"mTimeUnit":600000,"mTotalActiveTime":0.0,"mWalkStepCount":0},{"mCalorie":0.0,"mDistance":0.0,"mNowHealthyStep":0,"mRunStepCount":0,"mSpeed":0.0,"mStartTime":0,"mStepCount":0,"mTimeUnit":600000,"mTotalActiveTime":0.0,"mWalkStepCount":0},{"mCalorie":0.0,"mDistance":0.0,"mNowHealthyStep":0,"mRunStepCount":0,"mSpeed":0.0,"mStartTime":0,"mStepCount":0,"mTimeUnit":600000,"mTotalActiveTime":0.0,"mWalkStepCount":0},{"mCalorie":0.0,"mDistance":0.0,"mNowHealthyStep":0,"mRunStepCount":0,"mSpeed":0.0,"mStartTime":0,"mStepCount":0,"mTimeUnit":600000,"mTotalActiveTime":0.0,"mWalkStepCount":0},{"mCalorie":0.0,"mDistance":0.0,"mNowHealthyStep":0,"mRunStepCount":0,"mSpeed":0.0,"mStartTime":0,"mStepCount":0,"mTimeUnit":600000,"mTotalActiveTime":0.0,"mWalkStepCount":0},{"mCalorie":0.0,"mDistance":0.0,"mNowHealthyStep":0,"mRunStepCount":0,"mSpeed":0.0,"mStartTime":0,"mStepCount":0,"mTimeUnit":600000,"mTotalActiveTime":0.0,"mWalkStepCount":0},{"mCalorie":0.0,"mDistance":0.0,"mNowHealthyStep":0,"mRunStepCount":0,"mSpeed":0.0,"mStartTime":0,"mStepCount":0,"mTimeUnit":600000,"mTotalActiveTime":0.0,"mWalkStepCount":0},{"mCalorie":0.0,"mDistance":0.0,"mNowHealthyStep":0,"mRunStepCount":0,"mSpeed":0.0,"mStartTime":0,"mStepCount":0,"mTimeUnit":600000,"mTotalActiveTime":0.0,"mWalkStepCount":0},{"mCalorie":0.0,"mDistance":0.0,"mNowHealthyStep":0,"mRunStepCount":0,"mSpeed":0.0,"mStartTime":0,"mStepCount":0,"mTimeUnit":600000,"mTotalActiveTime":0.0,"mWalkStepCount":0},{"mCalorie":0.0,"mDistance":0.0,"mNowHealthyStep":0,"mRunStepCount":0,"mSpeed":0.0,"mStartTime":0,"mStepCount":0,"mTimeUnit":600000,"mTotalActiveTime":0.0,"mWalkStepCount":0},{"mCalorie":0.0,"mDistance":0.0,"mNowHealthyStep":0,"mRunStepCount":0,"mSpeed":0.0,"mStartTime":0,"mStepCount":0,"mTimeUnit":600000,"mTotalActiveTime":0.0,"mWalkStepCount":0},{"mCalorie":0.0,"mDistance":0.0,"mNowHealthyStep":0,"mRunStepCount":0,"mSpeed":0.0,"mStartTime":0,"mStepCount":0,"mTimeUnit":600000,"mTotalActiveTime":0.0,"mWalkStepCount":0},{"mCalorie":0.0,"mDistance":0.0,"mNowHealthyStep":0,"mRunStepCount":0,"mSpeed":0.0,"mStartTime":0,"mStepCount":0,"mTimeUnit":600000,"mTotalActiveTime":0.0,"mWalkStepCount":0},{"mCalorie":0.0,"mDistance":0.0,"mNowHealthyStep":0,"mRunStepCount":0,"mSpeed":0.0,"mStartTime":0,"mStepCount":0,"mTimeUnit":600000,"mTotalActiveTime":0.0,"mWalkStepCount":0},{"mCalorie":0.0,"mDistance":0.0,"mNowHealthyStep":0,"mRunStepCount":0,"mSpeed":0.0,"mStartTime":0,"mStepCount":0,"mTimeUnit":600000,"mTotalActiveTime":0.0,"mWalkStepCount":0},{"mCalorie":0.0,"mDistance":0.0,"mNowHealthyStep":0,"mRunStepCount":0,"mSpeed":0.0,"mStartTime":0,"mStepCount":0,"mTimeUnit":600000,"mTotalActiveTime":0.0,"mWalkStepCount":0},{"mCalorie":0.0,"mDistance":0.0,"mNowHealthyStep":0,"mRunStepCount":0,"mSpeed":0.0,"mStartTime":0,"mStepCount":0,"mTimeUnit":600000,"mTotalActiveTime":0.0,"mWalkStepCount":0},{"mCalorie":0.0,"mDistance":0.0,"mNowHealthyStep":0,"mRunStepCount":0,"mSpeed":0.0,"mStartTime":0,"mStepCount":0,"mTimeUnit":600000,"mTotalActiveTime":0.0,"mWalkStepCount":0},{"mCalorie":0.0,"mDistance":0.0,"mNowHealthyStep":0,"mRunStepCount":0,"mSpeed":0.0,"mStartTime":0,"mStepCount":0,"mTimeUnit":600000,"mTotalActiveTime":0.0,"mWalkStepCount":0},{"mCalorie":0.0,"mDistance":0.0,"mNowHealthyStep":0,"mRunStepCount":0,"mSpeed":0.0,"mStartTime":0,"mStepCount":0,"mTimeUnit":600000,"mTotalActiveTime":0.0,"mWalkStepCount":0},{"mCalorie":0.0,"mDistance":0.0,"mNowHealthyStep":0,"mRunStepCount":0,"mSpeed":0.0,"mStartTime":0,"mStepCount":0,"mTimeUnit":600000,"mTotalActiveTime":0.0,"mWalkStepCount":0},{"mCalorie":0.0,"mDistance":0.0,"mNowHealthyStep":0,"mRunStepCount":0,"mSpeed":0.0,"mStartTime":0,"mStepCount":0,"mTimeUnit":600000,"mTotalActiveTime":0.0,"mWalkStepCount":0},{"mCalorie":0.0,"mDistance":0.0,"mNowHealthyStep":0,"mRunStepCount":0,"mSpeed":0.0,"mStartTime":0,"mStepCount":0,"mTimeUnit":600000,"mTotalActiveTime":0.0,"mWalkStepCount":0},{"mCalorie":0.0,"mDistance":0.0,"mNowHealthyStep":0,"mRunStepCount":0,"mSpeed":0.0,"mStartTime":0,"mStepCount":0,"mTimeUnit":600000,"mTotalActiveTime":0.0,"mWalkStepCount":0},{"mCalorie":0.0,"mDistance":0.0,"mNowHealthyStep":0,"mRunStepCount":0,"mSpeed":0.0,"mStartTime":0,"mStepCount":0,"mTimeUnit":600000,"mTotalActiveTime":0.0,"mWalkStepCount":0},{"mCalorie":0.0,"mDistance":0.0,"mNowHealthyStep":0,"mRunStepCount":0,"mSpeed":0.0,"mStartTime":0,"mStepCount":0,"mTimeUnit":600000,"mTotalActiveTime":0.0,"mWalkStepCount":0},{"mCalorie":0.0,"mDistance":0.0,"mNowHealthyStep":0,"mRunStepCount":0,"mSpeed":0.0,"mStartTime":0,"mStepCount":0,"mTimeUnit":600000,"mTotalActiveTime":0.0,"mWalkStepCount":0},{"mCalorie":0.1899999976158142,"mDistance":4.949999809265137,"mNowHealthyStep":0,"mRunStepCount":0,"mSpeed":11.40000057220459,"mStartTime":0,"mStepCount":6,"mTimeUnit":600000,"mTotalActiveTime":1563.1577560446008,"mWalkStepCount":6},{"mCalorie":0.23999999463558197,"mDistance":5.510000228881836,"mNowHealthyStep":0,"mRunStepCount":0,"mSpeed":5.999999523162842,"mStartTime":0,"mStepCount":7,"mTimeUnit":600000,"mTotalActiveTime":3306.0004000664076,"mWalkStepCount":7},{"mCalorie":0.0,"mDistance":0.0,"mNowHealthyStep":0,"mRunStepCount":0,"mSpeed":0.0,"mStartTime":0,"mStepCount":0,"mTimeUnit":600000,"mTotalActiveTime":0.0,"mWalkStepCount":0},{"mCalorie":0.0,"mDistance":0.0,"mNowHealthyStep":0,"mRunStepCount":0,"mSpeed":0.0,"mStartTime":0,"mStepCount":0,"mTimeUnit":600000,"mTotalActiveTime":0.0,"mWalkStepCount":0},{"mCalorie":0.28999999165534973,"mDistance":6.070000171661377,"mNowHealthyStep":0,"mRunStepCount":0,"mSpeed":4.536033630371094,"mStartTime":0,"mStepCount":8,"mTimeUnit":600000,"mTotalActiveTime":4817.424736816433,"mWalkStepCount":8},{"mCalorie":0.0,"mDistance":0.0,"mNowHealthyStep":0,"mRunStepCount":0,"mSpeed":0.0,"mStartTime":0,"mStepCount":0,"mTimeUnit":600000,"mTotalActiveTime":0.0,"mWalkStepCount":0},{"mCalorie":0.0,"mDistance":0.0,"mNowHealthyStep":0,"mRunStepCount":0,"mSpeed":0.0,"mStartTime":0,"mStepCount":0,"mTimeUnit":600000,"mTotalActiveTime":0.0,"mWalkStepCount":0},{"mCalorie":33.720001220703125,"mDistance":786.8399887084961,"mNowHealthyStep":0,"mRunStepCount":30,"mSpeed":6.223752021789551,"mStartTime":0,"mStepCount":995,"mTimeUnit":600000,"mTotalActiveTime":455131.24145572446,"mWalkStepCount":965},{"mCalorie":0.4000000059604645,"mDistance":9.489999771118164,"mNowHealthyStep":0,"mRunStepCount":0,"mSpeed":5.600000381469727,"mStartTime":0,"mStepCount":12,"mTimeUnit":600000,"mTotalActiveTime":6100.713722997821,"mWalkStepCount":12},{"mCalorie":3.769999921321869,"mDistance":87.74000263214111,"mNowHealthyStep":0,"mRunStepCount":0,"mSpeed":5.576617240905762,"mStartTime":0,"mStepCount":111,"mTimeUnit":600000,"mTotalActiveTime":56640.78843080254,"mWalkStepCount":111},{"mCalorie":48.10999834537506,"mDistance":602.3500289916992,"mNowHealthyStep":0,"mRunStepCount":0,"mSpeed":5.5740814208984375,"mStartTime":0,"mStepCount":956,"mTimeUnit":600000,"mTotalActiveTime":389025.5668643847,"mWalkStepCount":956},{"mCalorie":6.239999353885651,"mDistance":138.7899990081787,"mNowHealthyStep":0,"mRunStepCount":0,"mSpeed":5.343398571014404,"mStartTime":0,"mStepCount":180,"mTimeUnit":600000,"mTotalActiveTime":93506.78316154437,"mWalkStepCount":180},{"mCalorie":2.3399999886751175,"mDistance":52.42999887466431,"mNowHealthyStep":0,"mRunStepCount":0,"mSpeed":5.828886985778809,"mStartTime":0,"mStepCount":67,"mTimeUnit":600000,"mTotalActiveTime":32381.48025869643,"mWalkStepCount":67},{"mCalorie":1.5799999833106995,"mDistance":37.37000036239624,"mNowHealthyStep":0,"mRunStepCount":0,"mSpeed":6.1778693199157715,"mStartTime":0,"mStepCount":47,"mTimeUnit":600000,"mTotalActiveTime":21776.44018173629,"mWalkStepCount":47},{"mCalorie":1.0499999821186066,"mDistance":22.65000009536743,"mNowHealthyStep":0,"mRunStepCount":0,"mSpeed":5.609821796417236,"mStartTime":0,"mStepCount":29,"mTimeUnit":600000,"mTotalActiveTime":14535.220639628744,"mWalkStepCount":29},{"mCalorie":1.4500000029802322,"mDistance":32.230000019073486,"mNowHealthyStep":0,"mRunStepCount":0,"mSpeed":5.279477119445801,"mStartTime":0,"mStepCount":42,"mTimeUnit":600000,"mTotalActiveTime":21977.17644243022,"mWalkStepCount":42},{"mCalorie":0.0,"mDistance":0.0,"mNowHealthyStep":0,"mRunStepCount":0,"mSpeed":0.0,"mStartTime":0,"mStepCount":0,"mTimeUnit":600000,"mTotalActiveTime":0.0,"mWalkStepCount":0},{"mCalorie":1.0700000524520874,"mDistance":23.729999542236328,"mNowHealthyStep":0,"mRunStepCount":0,"mSpeed":5.5,"mStartTime":0,"mStepCount":31,"mTimeUnit":600000,"mTotalActiveTime":15532.363336736507,"mWalkStepCount":31},{"mCalorie":0.0,"mDistance":0.0,"mNowHealthyStep":0,"mRunStepCount":0,"mSpeed":0.0,"mStartTime":0,"mStepCount":0,"mTimeUnit":600000,"mTotalActiveTime":0.0,"mWalkStepCount":0},{"mCalorie":3.0799989700317383,"mDistance":76.68000030517578,"mNowHealthyStep":0,"mRunStepCount":0,"mSpeed":5.705080986022949,"mStartTime":0,"mStepCount":98,"mTimeUnit":600000,"mTotalActiveTime":48386.34365498026,"mWalkStepCount":98},{"mCalorie":0.0,"mDistance":0.0,"mNowHealthyStep":0,"mRunStepCount":0,"mSpeed":0.0,"mStartTime":0,"mStepCount":0,"mTimeUnit":600000,"mTotalActiveTime":0.0,"mWalkStepCount":0},{"mCalorie":0.5400000214576721,"mDistance":13.149999618530273,"mNowHealthyStep":0,"mRunStepCount":0,"mSpeed":6.700000286102295,"mStartTime":0,"mStepCount":16,"mTimeUnit":600000,"mTotalActiveTime":7065.671135105113,"mWalkStepCount":16},{"mCalorie":2.1600000262260437,"mDistance":46.86000156402588,"mNowHealthyStep":0,"mRunStepCount":0,"mSpeed":5.264115810394287,"mStartTime":0,"mStepCount":61,"mTimeUnit":600000,"mTotalActiveTime":32046.408695633305,"mWalkStepCount":61},{"mCalorie":1.1199999302625656,"mDistance":26.36000108718872,"mNowHealthyStep":0,"mRunStepCount":0,"mSpeed":6.2183990478515625,"mStartTime":0,"mStepCount":33,"mTimeUnit":600000,"mTotalActiveTime":15260.520562200858,"mWalkStepCount":33},{"mCalorie":1.1299998760223389,"mDistance":25.200002670288086,"mNowHealthyStep":0,"mRunStepCount":0,"mSpeed":5.958779811859131,"mStartTime":0,"mStepCount":31,"mTimeUnit":600000,"mTotalActiveTime":15224.595047544237,"mWalkStepCount":31},{"mCalorie":1.0399999767541885,"mDistance":25.27999973297119,"mNowHealthyStep":0,"mRunStepCount":0,"mSpeed":6.034426212310791,"mStartTime":0,"mStepCount":32,"mTimeUnit":600000,"mTotalActiveTime":15081.467346282292,"mWalkStepCount":32},{"mCalorie":1.590000033378601,"mDistance":38.400001525878906,"mNowHealthyStep":0,"mRunStepCount":0,"mSpeed":5.5,"mStartTime":0,"mStepCount":49,"mTimeUnit":600000,"mTotalActiveTime":25134.54645330256,"mWalkStepCount":49},{"mCalorie":0.0,"mDistance":0.0,"mNowHealthyStep":0,"mRunStepCount":0,"mSpeed":0.0,"mStartTime":0,"mStepCount":0,"mTimeUnit":600000,"mTotalActiveTime":0.0,"mWalkStepCount":0},{"mCalorie":0.0,"mDistance":0.0,"mNowHealthyStep":0,"mRunStepCount":0,"mSpeed":0.0,"mStartTime":0,"mStepCount":0,"mTimeUnit":600000,"mTotalActiveTime":0.0,"mWalkStepCount":0},{"mCalorie":2.3299989700317383,"mDistance":42.759986877441406,"mNowHealthyStep":0,"mRunStepCount":0,"mSpeed":4.583090782165527,"mStartTime":0,"mStepCount":59,"mTimeUnit":600000,"mTotalActiveTime":33587.80353158393,"mWalkStepCount":59},{"mCalorie":24.31000006198883,"mDistance":527.9600028991699,"mNowHealthyStep":0,"mRunStepCount":0,"mSpeed":5.623666763305664,"mStartTime":0,"mStepCount":722,"mTimeUnit":600000,"mTotalActiveTime":337974.520854395,"mWalkStepCount":722},{"mCalorie":0.0,"mDistance":0.0,"mNowHealthyStep":0,"mRunStepCount":0,"mSpeed":0.0,"mStartTime":0,"mStepCount":0,"mTimeUnit":600000,"mTotalActiveTime":0.0,"mWalkStepCount":0},{"mCalorie":23.299999713897705,"mDistance":429.2899971008301,"mNowHealthyStep":0,"mRunStepCount":0,"mSpeed":5.094234466552734,"mStartTime":0,"mStepCount":577,"mTimeUnit":600000,"mTotalActiveTime":303371.18740662496,"mWalkStepCount":577},{"mCalorie":8.529998570680618,"mDistance":198.05999898910522,"mNowHealthyStep":0,"mRunStepCount":0,"mSpeed":5.664057731628418,"mStartTime":0,"mStepCount":253,"mTimeUnit":600000,"mTotalActiveTime":125884.31382062248,"mWalkStepCount":253},{"mCalorie":0.5899999737739563,"mDistance":8.369999885559082,"mNowHealthyStep":0,"mRunStepCount":0,"mSpeed":7.499999523162842,"mStartTime":0,"mStepCount":7,"mTimeUnit":600000,"mTotalActiveTime":4017.600200500501,"mWalkStepCount":7},{"mCalorie":0.0,"mDistance":0.0,"mNowHealthyStep":0,"mRunStepCount":0,"mSpeed":0.0,"mStartTime":0,"mStepCount":0,"mTimeUnit":600000,"mTotalActiveTime":0.0,"mWalkStepCount":0},{"mCalorie":2.2899996042251587,"mDistance":56.31999206542969,"mNowHealthyStep":0,"mRunStepCount":0,"mSpeed":6.079333782196045,"mStartTime":0,"mStepCount":71,"mTimeUnit":600000,"mTotalActiveTime":33351.01797650108,"mWalkStepCount":71},{"mCalorie":4.699999213218689,"mDistance":118.47001647949219,"mNowHealthyStep":0,"mRunStepCount":0,"mSpeed":6.0450897216796875,"mStartTime":0,"mStepCount":147,"mTimeUnit":600000,"mTotalActiveTime":70551.8178625164,"mWalkStepCount":147},{"mCalorie":0.0,"mDistance":0.0,"mNowHealthyStep":0,"mRunStepCount":0,"mSpeed":0.0,"mStartTime":0,"mStepCount":0,"mTimeUnit":600000,"mTotalActiveTime":0.0,"mWalkStepCount":0},{"mCalorie":0.0,"mDistance":0.0,"mNowHealthyStep":0,"mRunStepCount":0,"mSpeed":0.0,"mStartTime":0,"mStepCount":0,"mTimeUnit":600000,"mTotalActiveTime":0.0,"mWalkStepCount":0},{"mCalorie":0.550000011920929,"mDistance":7.889999866485596,"mNowHealthyStep":0,"mRunStepCount":0,"mSpeed":6.900000095367432,"mStartTime":0,"mStepCount":6,"mTimeUnit":600000,"mTotalActiveTime":4116.521612574789,"mWalkStepCount":6},{"mCalorie":4.67000013589859,"mDistance":107.51000213623047,"mNowHealthyStep":0,"mRunStepCount":0,"mSpeed":5.437279224395752,"mStartTime":0,"mStepCount":139,"mTimeUnit":600000,"mTotalActiveTime":71181.92764047359,"mWalkStepCount":139},{"mCalorie":0.0,"mDistance":0.0,"mNowHealthyStep":0,"mRunStepCount":0,"mSpeed":0.0,"mStartTime":0,"mStepCount":0,"mTimeUnit":600000,"mTotalActiveTime":0.0,"mWalkStepCount":0},{"mCalorie":0.0,"mDistance":0.0,"mNowHealthyStep":0,"mRunStepCount":0,"mSpeed":0.0,"mStartTime":0,"mStepCount":0,"mTimeUnit":600000,"mTotalActiveTime":0.0,"mWalkStepCount":0},{"mCalorie":0.0,"mDistance":0.0,"mNowHealthyStep":0,"mRunStepCount":0,"mSpeed":0.0,"mStartTime":0,"mStepCount":0,"mTimeUnit":600000,"mTotalActiveTime":0.0,"mWalkStepCount":0},{"mCalorie":0.0,"mDistance":0.0,"mNowHealthyStep":0,"mRunStepCount":0,"mSpeed":0.0,"mStartTime":0,"mStepCount":0,"mTimeUnit":600000,"mTotalActiveTime":0.0,"mWalkStepCount":0},{"mCalorie":0.0,"mDistance":0.0,"mNowHealthyStep":0,"mRunStepCount":0,"mSpeed":0.0,"mStartTime":0,"mStepCount":0,"mTimeUnit":600000,"mTotalActiveTime":0.0,"mWalkStepCount":0},{"mCalorie":0.0,"mDistance":0.0,"mNowHealthyStep":0,"mRunStepCount":0,"mSpeed":0.0,"mStartTime":0,"mStepCount":0,"mTimeUnit":600000,"mTotalActiveTime":0.0,"mWalkStepCount":0},{"mCalorie":0.0,"mDistance":0.0,"mNowHealthyStep":0,"mRunStepCount":0,"mSpeed":0.0,"mStartTime":0,"mStepCount":0,"mTimeUnit":600000,"mTotalActiveTime":0.0,"mWalkStepCount":0},{"mCalorie":0.0,"mDistance":0.0,"mNowHealthyStep":0,"mRunStepCount":0,"mSpeed":0.0,"mStartTime":0,"mStepCount":0,"mTimeUnit":600000,"mTotalActiveTime":0.0,"mWalkStepCount":0},{"mCalorie":0.0,"mDistance":0.0,"mNowHealthyStep":0,"mRunStepCount":0,"mSpeed":0.0,"mStartTime":0,"mStepCount":0,"mTimeUnit":600000,"mTotalActiveTime":0.0,"mWalkStepCount":0},{"mCalorie":0.0,"mDistance":0.0,"mNowHealthyStep":0,"mRunStepCount":0,"mSpeed":0.0,"mStartTime":0,"mStepCount":0,"mTimeUnit":600000,"mTotalActiveTime":0.0,"mWalkStepCount":0},{"mCalorie":0.0,"mDistance":0.0,"mNowHealthyStep":0,"mRunStepCount":0,"mSpeed":0.0,"mStartTime":0,"mStepCount":0,"mTimeUnit":600000,"mTotalActiveTime":0.0,"mWalkStepCount":0},{"mCalorie":0.0,"mDistance":0.0,"mNowHealthyStep":0,"mRunStepCount":0,"mSpeed":0.0,"mStartTime":0,"mStepCount":0,"mTimeUnit":600000,"mTotalActiveTime":0.0,"mWalkStepCount":0},{"mCalorie":0.0,"mDistance":0.0,"mNowHealthyStep":0,"mRunStepCount":0,"mSpeed":0.0,"mStartTime":0,"mStepCount":0,"mTimeUnit":600000,"mTotalActiveTime":0.0,"mWalkStepCount":0},{"mCalorie":0.0,"mDistance":0.0,"mNowHealthyStep":0,"mRunStepCount":0,"mSpeed":0.0,"mStartTime":0,"mStepCount":0,"mTimeUnit":600000,"mTotalActiveTime":0.0,"mWalkStepCount":0},{"mCalorie":0.0,"mDistance":0.0,"mNowHealthyStep":0,"mRunStepCount":0,"mSpeed":0.0,"mStartTime":0,"mStepCount":0,"mTimeUnit":600000,"mTotalActiveTime":0.0,"mWalkStepCount":0},{"mCalorie":0.0,"mDistance":0.0,"mNowHealthyStep":0,"mRunStepCount":0,"mSpeed":0.0,"mStartTime":0,"mStepCount":0,"mTimeUnit":600000,"mTotalActiveTime":0.0,"mWalkStepCount":0},{"mCalorie":0.0,"mDistance":0.0,"mNowHealthyStep":0,"mRunStepCount":0,"mSpeed":0.0,"mStartTime":0,"mStepCount":0,"mTimeUnit":600000,"mTotalActiveTime":0.0,"mWalkStepCount":0},{"mCalorie":0.0,"mDistance":0.0,"mNowHealthyStep":0,"mRunStepCount":0,"mSpeed":0.0,"mStartTime":0,"mStepCount":0,"mTimeUnit":600000,"mTotalActiveTime":0.0,"mWalkStepCount":0},{"mCalorie":2.259999692440033,"mDistance":46.30000972747803,"mNowHealthyStep":0,"mRunStepCount":0,"mSpeed":5.140700817108154,"mStartTime":0,"mStepCount":61,"mTimeUnit":600000,"mTotalActiveTime":32423.602596030476,"mWalkStepCount":61},{"mCalorie":6.620000064373016,"mDistance":120.81000185012817,"mNowHealthyStep":0,"mRunStepCount":41,"mSpeed":7.727573394775391,"mStartTime":0,"mStepCount":133,"mTimeUnit":600000,"mTotalActiveTime":56281.05844001626,"mWalkStepCount":92},{"mCalorie":2.3100000619888306,"mDistance":57.35000038146973,"mNowHealthyStep":0,"mRunStepCount":0,"mSpeed":5.630075931549072,"mStartTime":0,"mStepCount":73,"mTimeUnit":600000,"mTotalActiveTime":36670.91011957693,"mWalkStepCount":73},{"mCalorie":5.179999589920044,"mDistance":113.84000587463379,"mNowHealthyStep":0,"mRunStepCount":0,"mSpeed":5.391047954559326,"mStartTime":0,"mStepCount":148,"mTimeUnit":600000,"mTotalActiveTime":76019.36212209293,"mWalkStepCount":148},{"mCalorie":0.0,"mDistance":0.0,"mNowHealthyStep":0,"mRunStepCount":0,"mSpeed":0.0,"mStartTime":0,"mStepCount":0,"mTimeUnit":600000,"mTotalActiveTime":0.0,"mWalkStepCount":0},{"mCalorie":0.0,"mDistance":0.0,"mNowHealthyStep":0,"mRunStepCount":0,"mSpeed":0.0,"mStartTime":0,"mStepCount":0,"mTimeUnit":600000,"mTotalActiveTime":0.0,"mWalkStepCount":0},{"mCalorie":0.0,"mDistance":0.0,"mNowHealthyStep":0,"mRunStepCount":0,"mSpeed":0.0,"mStartTime":0,"mStepCount":0,"mTimeUnit":600000,"mTotalActiveTime":0.0,"mWalkStepCount":0},{"mCalorie":0.0,"mDistance":0.0,"mNowHealthyStep":0,"mRunStepCount":0,"mSpeed":0.0,"mStartTime":0,"mStepCount":0,"mTimeUnit":600000,"mTotalActiveTime":0.0,"mWalkStepCount":0},{"mCalorie":0.0,"mDistance":0.0,"mNowHealthyStep":0,"mRunStepCount":0,"mSpeed":0.0,"mStartTime":0,"mStepCount":0,"mTimeUnit":600000,"mTotalActiveTime":0.0,"mWalkStepCount":0},{"mCalorie":0.0,"mDistance":0.0,"mNowHealthyStep":0,"mRunStepCount":0,"mSpeed":0.0,"mStartTime":0,"mStepCount":0,"mTimeUnit":600000,"mTotalActiveTime":0.0,"mWalkStepCount":0},{"mCalorie":0.0,"mDistance":0.0,"mNowHealthyStep":0,"mRunStepCount":0,"mSpeed":0.0,"mStartTime":0,"mStepCount":0,"mTimeUnit":600000,"mTotalActiveTime":0.0,"mWalkStepCount":0},{"mCalorie":0.0,"mDistance":0.0,"mNowHealthyStep":0,"mRunStepCount":0,"mSpeed":0.0,"mStartTime":0,"mStepCount":0,"mTimeUnit":600000,"mTotalActiveTime":0.0,"mWalkStepCount":0},{"mCalorie":0.0,"mDistance":0.0,"mNowHealthyStep":0,"mRunStepCount":0,"mSpeed":0.0,"mStartTime":0,"mStepCount":0,"mTimeUnit":600000,"mTotalActiveTime":0.0,"mWalkStepCount":0},{"mCalorie":0.0,"mDistance":0.0,"mNowHealthyStep":0,"mRunStepCount":0,"mSpeed":0.0,"mStartTime":0,"mStepCount":0,"mTimeUnit":600000,"mTotalActiveTime":0.0,"mWalkStepCount":0},{"mCalorie":0.0,"mDistance":0.0,"mNowHealthyStep":0,"mRunStepCount":0,"mSpeed":0.0,"mStartTime":0,"mStepCount":0,"mTimeUnit":600000,"mTotalActiveTime":0.0,"mWalkStepCount":0},{"mCalorie":0.0,"mDistance":0.0,"mNowHealthyStep":0,"mRunStepCount":0,"mSpeed":0.0,"mStartTime":0,"mStepCount":0,"mTimeUnit":600000,"mTotalActiveTime":0.0,"mWalkStepCount":0},{"mCalorie":22.479992866516113,"mDistance":385.2101173400879,"mNowHealthyStep":0,"mRunStepCount":89,"mSpeed":7.146798610687256,"mStartTime":0,"mStepCount":559,"mTimeUnit":600000,"mTotalActiveTime":194038.83217971836,"mWalkStepCount":470},{"mCalorie":14.42999954521656,"mDistance":332.83997869491577,"mNowHealthyStep":0,"mRunStepCount":2,"mSpeed":6.161961555480957,"mStartTime":0,"mStepCount":451,"mTimeUnit":600000,"mTotalActiveTime":194454.94402124584,"mWalkStepCount":449},{"mCalorie":0.7699998021125793,"mDistance":19.139999389648438,"mNowHealthyStep":0,"mRunStepCount":0,"mSpeed":6.473413467407227,"mStartTime":0,"mStepCount":24,"mTimeUnit":600000,"mTotalActiveTime":10644.15213853662,"mWalkStepCount":24},{"mCalorie":0.0,"mDistance":0.0,"mNowHealthyStep":0,"mRunStepCount":0,"mSpeed":0.0,"mStartTime":0,"mStepCount":0,"mTimeUnit":600000,"mTotalActiveTime":0.0,"mWalkStepCount":0},{"mCalorie":25.519999384880066,"mDistance":629.900016784668,"mNowHealthyStep":0,"mRunStepCount":12,"mSpeed":5.970906734466553,"mStartTime":0,"mStepCount":793,"mTimeUnit":600000,"mTotalActiveTime":379781.523706215,"mWalkStepCount":781},{"mCalorie":12.719999827444553,"mDistance":314.569997549057,"mNowHealthyStep":0,"mRunStepCount":9,"mSpeed":6.347596168518066,"mStartTime":0,"mStepCount":389,"mTimeUnit":600000,"mTotalActiveTime":178406.43522556635,"mWalkStepCount":380},{"mCalorie":29.339999556541443,"mDistance":552.1300601959229,"mNowHealthyStep":0,"mRunStepCount":152,"mSpeed":6.916313648223877,"mStartTime":0,"mStepCount":632,"mTimeUnit":600000,"mTotalActiveTime":287388.37812160794,"mWalkStepCount":480},{"mCalorie":0.0,"mDistance":0.0,"mNowHealthyStep":0,"mRunStepCount":0,"mSpeed":0.0,"mStartTime":0,"mStepCount":0,"mTimeUnit":600000,"mTotalActiveTime":0.0,"mWalkStepCount":0},{"mCalorie":0.0,"mDistance":0.0,"mNowHealthyStep":0,"mRunStepCount":0,"mSpeed":0.0,"mStartTime":0,"mStepCount":0,"mTimeUnit":600000,"mTotalActiveTime":0.0,"mWalkStepCount":0},{"mCalorie":0.0,"mDistance":0.0,"mNowHealthyStep":0,"mRunStepCount":0,"mSpeed":0.0,"mStartTime":0,"mStepCount":0,"mTimeUnit":600000,"mTotalActiveTime":0.0,"mWalkStepCount":0},{"mCalorie":0.0,"mDistance":0.0,"mNowHealthyStep":0,"mRunStepCount":0,"mSpeed":0.0,"mStartTime":0,"mStepCount":0,"mTimeUnit":600000,"mTotalActiveTime":0.0,"mWalkStepCount":0},{"mCalorie":0.0,"mDistance":0.0,"mNowHealthyStep":0,"mRunStepCount":0,"mSpeed":0.0,"mStartTime":0,"mStepCount":0,"mTimeUnit":600000,"mTotalActiveTime":0.0,"mWalkStepCount":0},{"mCalorie":0.0,"mDistance":0.0,"mNowHealthyStep":0,"mRunStepCount":0,"mSpeed":0.0,"mStartTime":0,"mStepCount":0,"mTimeUnit":600000,"mTotalActiveTime":0.0,"mWalkStepCount":0},{"mCalorie":0.0,"mDistance":0.0,"mNowHealthyStep":0,"mRunStepCount":0,"mSpeed":0.0,"mStartTime":0,"mStepCount":0,"mTimeUnit":600000,"mTotalActiveTime":0.0,"mWalkStepCount":0},{"mCalorie":0.0,"mDistance":0.0,"mNowHealthyStep":0,"mRunStepCount":0,"mSpeed":0.0,"mStartTime":0,"mStepCount":0,"mTimeUnit":600000,"mTotalActiveTime":0.0,"mWalkStepCount":0},{"mCalorie":21.249995231628418,"mDistance":517.4900455474854,"mNowHealthyStep":0,"mRunStepCount":0,"mSpeed":5.548365116119385,"mStartTime":0,"mStepCount":675,"mTimeUnit":600000,"mTotalActiveTime":335768.12849381054,"mWalkStepCount":675},{"mCalorie":35.9300000667572,"mDistance":760.1100006103516,"mNowHealthyStep":0,"mRunStepCount":25,"mSpeed":5.482990741729736,"mStartTime":0,"mStepCount":965,"mTimeUnit":600000,"mTotalActiveTime":499069.94711928826,"mWalkStepCount":940},{"mCalorie":20.930000364780426,"mDistance":479.01999282836914,"mNowHealthyStep":0,"mRunStepCount":16,"mSpeed":5.719208717346191,"mStartTime":0,"mStepCount":605,"mTimeUnit":600000,"mTotalActiveTime":301522.83310774947,"mWalkStepCount":589},{"mCalorie":21.579999953508377,"mDistance":476.0000057220459,"mNowHealthyStep":0,"mRunStepCount":47,"mSpeed":6.307100296020508,"mStartTime":0,"mStepCount":579,"mTimeUnit":600000,"mTotalActiveTime":271693.7954846128,"mWalkStepCount":532},{"mCalorie":5.400000095367432,"mDistance":140.03000259399414,"mNowHealthyStep":0,"mRunStepCount":0,"mSpeed":5.808640003204346,"mStartTime":0,"mStepCount":178,"mTimeUnit":600000,"mTotalActiveTime":86785.89606049749,"mWalkStepCount":178},{"mCalorie":0.0,"mDistance":0.0,"mNowHealthyStep":0,"mRunStepCount":0,"mSpeed":0.0,"mStartTime":0,"mStepCount":0,"mTimeUnit":600000,"mTotalActiveTime":0.0,"mWalkStepCount":0},{"mCalorie":1.7599995136260986,"mDistance":39.540008544921875,"mNowHealthyStep":0,"mRunStepCount":0,"mSpeed":5.507641315460205,"mStartTime":0,"mStepCount":51,"mTimeUnit":600000,"mTotalActiveTime":25844.82587167622,"mWalkStepCount":51},{"mCalorie":0.0,"mDistance":0.0,"mNowHealthyStep":0,"mRunStepCount":0,"mSpeed":0.0,"mStartTime":0,"mStepCount":0,"mTimeUnit":600000,"mTotalActiveTime":0.0,"mWalkStepCount":0},{"mCalorie":0.0,"mDistance":0.0,"mNowHealthyStep":0,"mRunStepCount":0,"mSpeed":0.0,"mStartTime":0,"mStepCount":0,"mTimeUnit":600000,"mTotalActiveTime":0.0,"mWalkStepCount":0},{"mCalorie":0.0,"mDistance":0.0,"mNowHealthyStep":0,"mRunStepCount":0,"mSpeed":0.0,"mStartTime":0,"mStepCount":0,"mTimeUnit":600000,"mTotalActiveTime":0.0,"mWalkStepCount":0},{"mCalorie":0.0,"mDistance":0.0,"mNowHealthyStep":0,"mRunStepCount":0,"mSpeed":0.0,"mStartTime":0,"mStepCount":0,"mTimeUnit":600000,"mTotalActiveTime":0.0,"mWalkStepCount":0}]